{"skeleton":{"hash":"rvLdgZjRdcvcK/rXGINKKru9ZLY","spine":"3.6.53","width":1546.3,"height":931.62},"bones":[{"name":"root"},{"name":"LIGHT","parent":"root"},{"name":"LIGHTLINE","parent":"LIGHT","length":352.72,"rotation":-65.94},{"name":"LIGHTLINE2","parent":"LIGHT","length":352.72,"rotation":-65.94},{"name":"LIGHTLINE3","parent":"LIGHT","length":352.72,"rotation":-65.94},{"name":"LIGHTLINE4","parent":"LIGHT","length":352.72,"rotation":-65.94},{"name":"LIGHTLINE6","parent":"LIGHT","length":352.72,"rotation":-65.94},{"name":"LIGHTLINE7","parent":"LIGHT","length":352.72,"rotation":-65.94},{"name":"LIGHTLOOP","parent":"LIGHT"},{"name":"bodyall","parent":"root","length":337.97,"rotation":92.01},{"name":"body","parent":"bodyall","length":94.92,"rotation":-1.78,"x":36.37,"y":-2.49},{"name":"head","parent":"body","length":206.73,"rotation":2.85,"x":93.19,"y":6.81},{"name":"Lear","parent":"head","length":45.1,"rotation":45.18,"x":164.47,"y":65.23},{"name":"Leye","parent":"head","rotation":-2.31,"x":103.41,"y":24.61},{"name":"Lleg","parent":"bodyall","length":51.48,"rotation":177.99,"x":51.63,"y":14.46},{"name":"Lfoot","parent":"Lleg","length":43.33,"rotation":-89.01,"x":47.26,"y":19.73},{"name":"Rear","parent":"head","length":47.54,"rotation":-52.34,"x":162.69,"y":-64.87},{"name":"Reye","parent":"head","rotation":-2.31,"x":101.54,"y":-31.62},{"name":"Rleg","parent":"bodyall","length":51.48,"rotation":177.99,"x":50.48,"y":-18.19},{"name":"Rfoot","parent":"Rleg","length":39.35,"rotation":90.73,"x":45.51,"y":-6.21},{"name":"STAR","parent":"LIGHT"},{"name":"STAR2","parent":"LIGHT"},{"name":"STAR3","parent":"LIGHT"},{"name":"STAR4","parent":"LIGHT"},{"name":"STAR5","parent":"LIGHT"},{"name":"STAR6","parent":"LIGHT"},{"name":"STAR7","parent":"LIGHT"},{"name":"STAR8","parent":"LIGHT"},{"name":"text","parent":"bodyall","rotation":-92.01,"x":319.25,"y":-656.91},{"name":"close","parent":"text","x":391.5,"y":84.5},{"name":"lhand","parent":"body","length":108.13,"rotation":130.31,"x":90.01,"y":29.98},{"name":"rhand","parent":"body","length":115.37,"rotation":-72.5,"x":91.25,"y":-30.91},{"name":"shadow","parent":"root","x":0.35,"y":0.45},{"name":"xin","parent":"bodyall","rotation":-2.7,"x":345.8,"y":-158.28}],"slots":[{"name":"star","bone":"STAR","attachment":"star"},{"name":"star2","bone":"STAR2","attachment":"star"},{"name":"star6","bone":"STAR6","attachment":"star"},{"name":"star3","bone":"STAR3","attachment":"star"},{"name":"star7","bone":"STAR7","attachment":"star"},{"name":"star4","bone":"STAR4","attachment":"star"},{"name":"star8","bone":"STAR8","attachment":"star"},{"name":"star5","bone":"STAR5","attachment":"star"},{"name":"light1","bone":"LIGHTLOOP","attachment":"light1"},{"name":"light","bone":"LIGHTLINE","attachment":"light"},{"name":"light4","bone":"LIGHTLINE4","attachment":"light"},{"name":"light2","bone":"LIGHTLINE2","attachment":"light"},{"name":"light6","bone":"LIGHTLINE6","attachment":"light"},{"name":"light3","bone":"LIGHTLINE3","attachment":"light"},{"name":"light7","bone":"LIGHTLINE7","attachment":"light"},{"name":"shadow","bone":"shadow","attachment":"shadow"},{"name":"xin","bone":"xin","attachment":"xin"},{"name":"rbi","bone":"rhand","attachment":"rbi"},{"name":"lbi","bone":"lhand","attachment":"lbi"},{"name":"rleg","bone":"Rleg","attachment":"rleg"},{"name":"rfoot","bone":"Rfoot","attachment":"rfoot"},{"name":"lleg","bone":"Lleg","attachment":"lleg"},{"name":"lfoot","bone":"Lfoot","attachment":"lfoot"},{"name":"body","bone":"body","attachment":"body"},{"name":"lear","bone":"Lear","attachment":"lear"},{"name":"rear","bone":"Rear","attachment":"rear"},{"name":"head","bone":"head","attachment":"head"},{"name":"reye","bone":"Reye","attachment":"reye"},{"name":"leye","bone":"Leye","attachment":"leye"},{"name":"text","bone":"text","attachment":"text"},{"name":"close","bone":"close","attachment":"close"}],"skins":{"default":{"body":{"body":{"x":61.68,"y":-0.07,"rotation":-90.23,"width":64,"height":129}},"close":{"close":{"width":38,"height":38}},"head":{"head":{"x":100.11,"y":-0.89,"rotation":-93.08,"width":271,"height":212}},"lbi":{"lbi":{"x":51.43,"y":0.37,"rotation":139.46,"width":102,"height":90}},"lear":{"lear":{"x":18.02,"y":1.61,"rotation":-138.26,"width":47,"height":47}},"leye":{"leye":{"x":0.58,"y":-0.15,"rotation":-90.77,"width":26,"height":61}},"lfoot":{"lfoot":{"x":22.3,"y":-8.67,"rotation":179.01,"width":54,"height":27}},"light":{"light":{"x":182.79,"y":-4.41,"rotation":65.94,"width":271,"height":469}},"light1":{"light1":{"width":899,"height":902}},"light2":{"light":{"x":182.79,"y":-4.41,"rotation":65.94,"width":271,"height":469}},"light3":{"light":{"x":182.79,"y":-4.41,"rotation":65.94,"width":271,"height":469}},"light4":{"light":{"x":182.79,"y":-4.41,"rotation":65.94,"width":271,"height":469}},"light6":{"light":{"x":182.79,"y":-4.41,"rotation":65.94,"width":271,"height":469}},"light7":{"light":{"x":182.79,"y":-4.41,"rotation":65.94,"width":271,"height":469}},"lleg":{"lleg":{"x":15.97,"y":3.29,"rotation":90,"width":38,"height":63}},"rbi":{"rbi":{"x":44.95,"y":0.11,"rotation":-17.74,"width":133,"height":68}},"rear":{"rear":{"x":23.14,"y":-0.69,"rotation":-40.74,"width":46,"height":47}},"reye":{"reye":{"x":1.43,"y":0.59,"rotation":-90.77,"width":27,"height":61}},"rfoot":{"rfoot":{"x":17.43,"y":7.82,"rotation":-0.73,"width":55,"height":26}},"rleg":{"rleg":{"x":17.97,"y":-0.88,"rotation":90,"width":39,"height":63}},"shadow":{"shadow":{"x":3.68,"y":0.67,"width":226,"height":27}},"star":{"star":{"width":154,"height":155}},"star2":{"star":{"width":154,"height":155}},"star3":{"star":{"width":154,"height":155}},"star4":{"star":{"width":154,"height":155}},"star5":{"star":{"width":154,"height":155}},"star6":{"star":{"width":154,"height":155}},"star7":{"star":{"width":154,"height":155}},"star8":{"star":{"width":154,"height":155}},"text":{"text":{"width":903,"height":277}},"xin":{"xin":{"x":0.56,"y":-0.85,"rotation":-89.32,"width":85,"height":84}}}},"animations":{"fault":{"slots":{"body":{"color":[{"time":0,"color":"ffffff00","curve":[0.25,0,0.75,1]},{"time":0.2333,"color":"ffffffff"}]},"head":{"color":[{"time":0,"color":"ffffff00","curve":[0.25,0,0.75,1]},{"time":0.2667,"color":"ffffffff"}]},"lbi":{"color":[{"time":0,"color":"ffffff00","curve":[0.25,0,0.75,1]},{"time":0.2333,"color":"ffffffff"}]},"lear":{"color":[{"time":0,"color":"ffffff00","curve":[0.25,0,0.75,1]},{"time":0.2333,"color":"ffffffff"}]},"leye":{"color":[{"time":0,"color":"ffffff00","curve":[0.25,0,0.75,1]},{"time":0.2333,"color":"ffffffff"}]},"lfoot":{"color":[{"time":0,"color":"ffffff00","curve":[0.25,0,0.75,1]},{"time":0.2333,"color":"ffffffff"}]},"light":{"attachment":[{"time":0,"name":null}]},"light1":{"attachment":[{"time":0,"name":null}]},"light2":{"attachment":[{"time":0,"name":null}]},"light3":{"attachment":[{"time":0,"name":null}]},"light4":{"attachment":[{"time":0,"name":null}]},"light6":{"attachment":[{"time":0,"name":null}]},"light7":{"attachment":[{"time":0,"name":null}]},"lleg":{"color":[{"time":0,"color":"ffffff00","curve":[0.25,0,0.75,1]},{"time":0.2333,"color":"ffffffff"}]},"rbi":{"color":[{"time":0,"color":"ffffff00","curve":[0.25,0,0.75,1]},{"time":0.2667,"color":"ffffffff"}]},"rear":{"color":[{"time":0,"color":"ffffff00","curve":[0.25,0,0.75,1]},{"time":0.2333,"color":"ffffffff"}]},"reye":{"color":[{"time":0,"color":"ffffff00","curve":[0.25,0,0.75,1]},{"time":0.2333,"color":"ffffffff"}],"attachment":[{"time":0.2333,"name":"reye"}]},"rfoot":{"color":[{"time":0,"color":"ffffff00","curve":[0.25,0,0.75,1]},{"time":0.2333,"color":"ffffffff"}]},"rleg":{"color":[{"time":0,"color":"ffffff00","curve":[0.25,0,0.75,1]},{"time":0.2333,"color":"ffffffff"}]},"shadow":{"color":[{"time":0,"color":"ffffff00","curve":[0.25,0,0.75,1]},{"time":0.2333,"color":"ffffffff"}]},"star":{"attachment":[{"time":0,"name":null}]},"star2":{"attachment":[{"time":0,"name":null}]},"star3":{"attachment":[{"time":0,"name":null}]},"star4":{"attachment":[{"time":0,"name":null}]},"star5":{"attachment":[{"time":0,"name":null}]},"star6":{"attachment":[{"time":0,"name":null}]},"star7":{"attachment":[{"time":0,"name":null}]},"star8":{"attachment":[{"time":0,"name":null}]},"xin":{"color":[{"time":0,"color":"ffffff00","curve":[0.25,0,0.75,1]},{"time":0.8333,"color":"ffffffff"}]}},"bones":{"bodyall":{"rotate":[{"time":0,"angle":0,"curve":"stepped"},{"time":0.1333,"angle":0,"curve":"stepped"},{"time":0.2667,"angle":0,"curve":"stepped"},{"time":0.4333,"angle":0,"curve":[0.25,0,0.75,1]},{"time":0.5667,"angle":0.3,"curve":[0.272,0,0.619,0.41]},{"time":0.7667,"angle":0,"curve":"stepped"},{"time":1.0667,"angle":0}],"translate":[{"time":0,"x":-159.07,"y":-5.59,"curve":[0.276,0,0.621,0.4]},{"time":0.1333,"x":-120.8,"y":24.44,"curve":[0.314,0.27,0.657,0.64]},{"time":0.2667,"x":-73.56,"y":75.8},{"time":0.4333,"x":0,"y":0,"curve":"stepped"},{"time":0.5667,"x":0,"y":0,"curve":"stepped"},{"time":0.7667,"x":0,"y":0,"curve":"stepped"},{"time":1.0667,"x":0,"y":0}],"scale":[{"time":0.1333,"x":1,"y":1,"curve":"stepped"},{"time":0.2667,"x":1,"y":1,"curve":"stepped"},{"time":0.4333,"x":1,"y":1,"curve":"stepped"},{"time":0.5667,"x":1,"y":1,"curve":"stepped"},{"time":0.7667,"x":1,"y":1,"curve":"stepped"},{"time":1.0667,"x":1,"y":1}]},"root":{"rotate":[{"time":0,"angle":0,"curve":"stepped"},{"time":0.1333,"angle":0,"curve":"stepped"},{"time":0.2667,"angle":0,"curve":"stepped"},{"time":0.4,"angle":0,"curve":[0.281,0,0.623,0.39]},{"time":0.5667,"angle":0.3,"curve":[0.312,0.26,0.653,0.62]},{"time":0.7667,"angle":0,"curve":"stepped"},{"time":0.8333,"angle":0,"curve":"stepped"},{"time":1,"angle":0,"curve":"stepped"},{"time":1.1667,"angle":0,"curve":"stepped"},{"time":1.3333,"angle":0}],"translate":[{"time":0,"x":0,"y":0,"curve":"stepped"},{"time":0.1333,"x":0,"y":0,"curve":"stepped"},{"time":0.4,"x":0,"y":0,"curve":"stepped"},{"time":0.5667,"x":0,"y":0,"curve":"stepped"},{"time":0.7667,"x":0,"y":0,"curve":"stepped"},{"time":0.8333,"x":0,"y":0,"curve":"stepped"},{"time":1,"x":0,"y":0,"curve":"stepped"},{"time":1.1667,"x":0,"y":0}],"scale":[{"time":0.1333,"x":1,"y":1,"curve":"stepped"},{"time":0.2667,"x":1,"y":1,"curve":"stepped"},{"time":0.4,"x":1,"y":1,"curve":"stepped"},{"time":0.5667,"x":1,"y":1,"curve":"stepped"},{"time":0.7667,"x":1,"y":1,"curve":"stepped"},{"time":0.8333,"x":1,"y":1,"curve":"stepped"},{"time":1,"x":1,"y":1,"curve":"stepped"},{"time":1.1667,"x":1,"y":1}]},"lhand":{"rotate":[{"time":0,"angle":0,"curve":[0.25,0,0.75,1]},{"time":0.1333,"angle":22.72,"curve":[0.25,0,0.75,1]},{"time":0.2667,"angle":14.09,"curve":[0.254,0,0.621,0.47]},{"time":0.4,"angle":-28.39,"curve":[0.333,0.33,0.67,0.68]},{"time":0.5667,"angle":4.26,"curve":[0.344,0.37,0.681,0.71]},{"time":0.9333,"angle":-32.86,"curve":[0.379,0.6,0.724,1]},{"time":1.2,"angle":7.04,"curve":[0.381,0.55,0.742,1]},{"time":1.3333,"angle":0.92,"curve":[0.381,0.55,0.742,1]},{"time":1.8333,"angle":3.68,"curve":[0.25,0,0.75,1]},{"time":2.4333,"angle":7.04,"curve":[0.381,0.55,0.742,1]},{"time":3.0667,"angle":3.68}],"translate":[{"time":0,"x":0,"y":0,"curve":"stepped"},{"time":0.1333,"x":0,"y":0,"curve":[0.268,0,0.618,0.42]},{"time":0.2667,"x":14.96,"y":-10.18,"curve":[0.321,0.3,0.668,0.67]},{"time":0.4,"x":0,"y":0,"curve":[0.382,0.55,0.741,1]},{"time":1.2,"x":-1.87,"y":-6.8,"curve":[0.381,0.55,0.742,1]},{"time":1.3333,"x":-2.95,"y":-10.76,"curve":[0.25,0,0.75,1]},{"time":1.8333,"x":0,"y":0,"curve":[0.25,0,0.75,1]},{"time":2.4333,"x":-1.87,"y":-6.8,"curve":[0.381,0.55,0.742,1]},{"time":3.0667,"x":0,"y":0}],"scale":[{"time":0.1333,"x":1,"y":1,"curve":"stepped"},{"time":0.2667,"x":1,"y":1,"curve":"stepped"},{"time":0.4,"x":1,"y":1,"curve":"stepped"},{"time":1.3333,"x":1,"y":1,"curve":"stepped"},{"time":1.8333,"x":1,"y":1,"curve":"stepped"},{"time":2.4333,"x":1,"y":1,"curve":"stepped"},{"time":3.0667,"x":1,"y":1}]},"rhand":{"rotate":[{"time":0,"angle":-10.04,"curve":"stepped"},{"time":0.1333,"angle":-10.04,"curve":"stepped"},{"time":0.2667,"angle":-10.04,"curve":"stepped"},{"time":0.4,"angle":-10.04,"curve":[0.334,0.33,0.67,0.68]},{"time":0.5667,"angle":-34.09,"curve":[0.344,0.37,0.681,0.72]},{"time":0.9333,"angle":-15.67,"curve":[0.379,0.6,0.723,1]},{"time":1.2,"angle":-48.3,"curve":[0.381,0.55,0.742,1]},{"time":1.3333,"angle":-42.7,"curve":[0.381,0.55,0.742,1]},{"time":1.8333,"angle":-46.17,"curve":[0.25,0,0.75,1]},{"time":2.4333,"angle":-48.3,"curve":[0.381,0.55,0.742,1]},{"time":3.0667,"angle":-46.17}],"translate":[{"time":0,"x":0,"y":0,"curve":"stepped"},{"time":0.1333,"x":0,"y":0,"curve":"stepped"},{"time":0.2667,"x":0,"y":0,"curve":"stepped"},{"time":0.4,"x":0,"y":0,"curve":[0.25,0,0.625,0.5]},{"time":1.2,"x":-4.84,"y":18.43,"curve":[0.381,0.55,0.742,1]},{"time":1.3333,"x":-4.77,"y":23.27,"curve":[0.25,0,0.75,1]},{"time":1.8333,"x":-4.96,"y":10.12,"curve":[0.25,0,0.75,1]},{"time":2.4333,"x":-4.84,"y":18.43,"curve":[0.381,0.55,0.742,1]},{"time":3.0667,"x":-4.96,"y":10.12}],"scale":[{"time":0,"x":1,"y":1,"curve":"stepped"},{"time":0.1333,"x":1,"y":1,"curve":"stepped"},{"time":0.2667,"x":1,"y":1,"curve":"stepped"},{"time":0.4,"x":1,"y":1,"curve":"stepped"},{"time":1.3333,"x":1,"y":1,"curve":"stepped"},{"time":1.8333,"x":1,"y":1,"curve":"stepped"},{"time":2.4333,"x":1,"y":1,"curve":"stepped"},{"time":3.0667,"x":1,"y":1}]},"Lleg":{"rotate":[{"time":0,"angle":0,"curve":[0.25,0,0.75,1]},{"time":0.1333,"angle":0.1,"curve":[0.25,0,0.75,1]},{"time":0.2667,"angle":-31.17,"curve":[0.25,0,0.75,1]},{"time":0.4,"angle":-21.9,"curve":[0.25,0,0.75,1]},{"time":0.5,"angle":0,"curve":[0.305,0,0.64,0.36]},{"time":0.5667,"angle":0.3,"curve":[0.294,0.18,0.638,0.55]},{"time":0.7667,"angle":0}],"translate":[{"time":0,"x":0,"y":0,"curve":[0.25,0,0.75,1]},{"time":0.1333,"x":-8.93,"y":0.31,"curve":[0.25,0,0.75,1]},{"time":0.4,"x":6.36,"y":5.93,"curve":[0.25,0,0.75,1]},{"time":0.5,"x":0,"y":0,"curve":"stepped"},{"time":0.5667,"x":0,"y":0,"curve":"stepped"},{"time":0.7667,"x":0,"y":0}],"scale":[{"time":0.1333,"x":1,"y":1,"curve":"stepped"},{"time":0.2667,"x":1,"y":1,"curve":"stepped"},{"time":0.4,"x":1,"y":1,"curve":"stepped"},{"time":0.5667,"x":1,"y":1,"curve":"stepped"},{"time":0.7667,"x":1,"y":1}]},"Rleg":{"rotate":[{"time":0,"angle":0,"curve":[0.25,0,0.75,1]},{"time":0.1333,"angle":-346.42,"curve":[0.25,0,0.75,1]},{"time":0.2667,"angle":-329.28,"curve":[0.25,0,0.75,1]},{"time":0.4,"angle":-278.83,"curve":[0.25,0,0.75,1]},{"time":0.5667,"angle":0.3,"curve":[0.272,0,0.619,0.41]},{"time":0.7667,"angle":0}],"translate":[{"time":0,"x":0,"y":0,"curve":[0.25,0,0.75,1]},{"time":0.1333,"x":-8.31,"y":-1.7,"curve":[0.25,0,0.625,0.5]},{"time":0.2667,"x":13.5,"y":9.77,"curve":[0.375,0.5,0.75,1]},{"time":0.4,"x":17.77,"y":4.45,"curve":[0.25,0,0.75,1]},{"time":0.5667,"x":0,"y":0,"curve":"stepped"},{"time":0.7667,"x":0,"y":0}],"scale":[{"time":0.1333,"x":1,"y":1,"curve":"stepped"},{"time":0.2667,"x":1,"y":1,"curve":"stepped"},{"time":0.4,"x":1,"y":1,"curve":"stepped"},{"time":0.5667,"x":1,"y":1,"curve":"stepped"},{"time":0.7667,"x":1,"y":1}]},"Rfoot":{"rotate":[{"time":0,"angle":0,"curve":[0.25,0,0.75,1]},{"time":0.1333,"angle":-29.6,"curve":[0.25,0,0.75,1]},{"time":0.2667,"angle":-45.78,"curve":[0.25,0,0.75,1]},{"time":0.4,"angle":-28.13,"curve":[0.281,0,0.623,0.39]},{"time":0.5667,"angle":13.03,"curve":[0.332,0.33,0.668,0.67]},{"time":0.6333,"angle":0,"curve":"stepped"},{"time":0.7667,"angle":0,"curve":"stepped"},{"time":0.8333,"angle":0,"curve":"stepped"},{"time":1,"angle":0,"curve":"stepped"},{"time":1.1667,"angle":0,"curve":"stepped"},{"time":1.3333,"angle":0}],"translate":[{"time":0,"x":0,"y":0,"curve":[0.25,0,0.75,1]},{"time":0.1333,"x":0.49,"y":-6.26,"curve":[0.25,0,0.75,1]},{"time":0.4,"x":0.01,"y":-1.08,"curve":[0.281,0,0.623,0.39]},{"time":0.5667,"x":0,"y":0,"curve":"stepped"},{"time":0.6333,"x":0,"y":0,"curve":"stepped"},{"time":0.7667,"x":0,"y":0,"curve":"stepped"},{"time":0.8333,"x":0,"y":0,"curve":"stepped"},{"time":1,"x":0,"y":0,"curve":"stepped"},{"time":1.1667,"x":0,"y":0}],"scale":[{"time":0,"x":1,"y":1,"curve":"stepped"},{"time":0.1333,"x":1,"y":1,"curve":"stepped"},{"time":0.2667,"x":1,"y":1,"curve":"stepped"},{"time":0.4,"x":1,"y":1,"curve":"stepped"},{"time":0.5667,"x":1,"y":1,"curve":"stepped"},{"time":0.6333,"x":1,"y":1,"curve":"stepped"},{"time":0.7667,"x":1,"y":1,"curve":"stepped"},{"time":0.8333,"x":1,"y":1,"curve":"stepped"},{"time":1,"x":1,"y":1,"curve":"stepped"},{"time":1.1667,"x":1,"y":1}]},"Lfoot":{"rotate":[{"time":0,"angle":0,"curve":[0.25,0,0.75,1]},{"time":0.1333,"angle":19.02,"curve":[0.25,0,0.75,1]},{"time":0.2667,"angle":33.17,"curve":[0.25,0,0.75,1]},{"time":0.4,"angle":0,"curve":[0.281,0,0.623,0.39]},{"time":0.5667,"angle":0.3,"curve":[0.312,0.26,0.653,0.62]},{"time":0.7667,"angle":0,"curve":"stepped"},{"time":0.8333,"angle":0,"curve":"stepped"},{"time":1,"angle":0,"curve":"stepped"},{"time":1.1667,"angle":0,"curve":"stepped"},{"time":1.3333,"angle":0}],"translate":[{"time":0,"x":0,"y":0,"curve":[0.25,0,0.75,1]},{"time":0.1333,"x":-2.83,"y":-1.03,"curve":[0.25,0,0.625,0.5]},{"time":0.2667,"x":-8.72,"y":-0.16,"curve":[0.375,0.5,0.75,1]},{"time":0.4,"x":0,"y":0,"curve":"stepped"},{"time":0.5667,"x":0,"y":0,"curve":"stepped"},{"time":0.7667,"x":0,"y":0,"curve":"stepped"},{"time":0.8333,"x":0,"y":0,"curve":"stepped"},{"time":1,"x":0,"y":0,"curve":"stepped"},{"time":1.1667,"x":0,"y":0}],"scale":[{"time":0,"x":1,"y":1,"curve":"stepped"},{"time":0.1333,"x":1,"y":1,"curve":"stepped"},{"time":0.2667,"x":1,"y":1,"curve":"stepped"},{"time":0.4,"x":1,"y":1,"curve":"stepped"},{"time":0.5667,"x":1,"y":1,"curve":"stepped"},{"time":0.7667,"x":1,"y":1,"curve":"stepped"},{"time":0.8333,"x":1,"y":1,"curve":"stepped"},{"time":1,"x":1,"y":1,"curve":"stepped"},{"time":1.1667,"x":1,"y":1}]},"head":{"rotate":[{"time":0,"angle":0,"curve":[0.25,0,0.75,1]},{"time":0.1333,"angle":-8.08,"curve":[0.245,0,0.64,0.57]},{"time":0.4,"angle":5.71,"curve":[0.382,0.55,0.741,1]},{"time":0.8,"angle":-1.74,"curve":[0.382,0.56,0.74,1]},{"time":1,"angle":-7.07,"curve":[0.25,0,0.75,1]},{"time":1.3333,"angle":6.17,"curve":[0.25,0,0.75,1]},{"time":1.8333,"angle":-8.19,"curve":[0.25,0,0.75,1]},{"time":2.4333,"angle":6.17,"curve":[0.25,0,0.75,1]},{"time":3.0667,"angle":-8.19}],"translate":[{"time":0,"x":0,"y":0,"curve":[0.25,0,0.75,1]},{"time":0.1333,"x":-20.06,"y":-3.29,"curve":[0.25,0,0.625,0.5]},{"time":0.2667,"x":-26.14,"y":-5.21,"curve":[0.375,0.5,0.75,1]},{"time":0.4,"x":0,"y":0,"curve":[0.25,0,0.75,1]},{"time":0.5667,"x":-7.2,"y":4.71,"curve":[0.25,0,0.75,1]},{"time":0.8,"x":-17,"y":1.16,"curve":[0.342,0.36,0.757,1]},{"time":1,"x":-33.7,"y":0.62,"curve":[0.25,0,0.75,1]},{"time":1.3333,"x":-45.63,"y":3.38,"curve":[0.25,0,0.75,1]},{"time":1.8333,"x":-44.03,"y":-7.7,"curve":[0.25,0,0.75,1]},{"time":2.4333,"x":-45.63,"y":3.38,"curve":[0.25,0,0.75,1]},{"time":3.0667,"x":-44.03,"y":-7.7}],"scale":[{"time":0,"x":1,"y":1,"curve":"stepped"},{"time":0.1333,"x":1,"y":1,"curve":"stepped"},{"time":0.2667,"x":1,"y":1,"curve":"stepped"},{"time":0.4,"x":1,"y":1,"curve":"stepped"},{"time":0.5667,"x":1,"y":1,"curve":[0.334,0.34,0.668,0.67]},{"time":0.6333,"x":0.696,"y":1,"curve":[0.346,0.38,0.685,0.73]},{"time":0.8,"x":0.878,"y":0.913,"curve":[0.378,0.61,0.721,1]},{"time":1,"x":0.906,"y":1,"curve":[0.276,0,0.621,0.4]},{"time":1.1667,"x":1.022,"y":1,"curve":[0.314,0.27,0.657,0.64]},{"time":1.3333,"x":1,"y":1,"curve":"stepped"},{"time":1.8333,"x":1,"y":1,"curve":"stepped"},{"time":2.4333,"x":1,"y":1,"curve":"stepped"},{"time":3.0667,"x":1,"y":1}]},"Leye":{"rotate":[{"time":0,"angle":0,"curve":"stepped"},{"time":0.1333,"angle":0,"curve":"stepped"},{"time":0.2333,"angle":0,"curve":[0.25,0,0.75,1]},{"time":0.4,"angle":0.3,"curve":[0.312,0.26,0.653,0.62]},{"time":0.7,"angle":-23.2,"curve":[0.25,0,0.75,1]},{"time":0.9,"angle":-8.34,"curve":[0.25,0,0.75,1]},{"time":1.0667,"angle":-23.2,"curve":"stepped"},{"time":1.3333,"angle":-23.2,"curve":"stepped"},{"time":1.8333,"angle":-23.2,"curve":"stepped"},{"time":2.4333,"angle":-23.2,"curve":"stepped"},{"time":3.0667,"angle":-23.2}],"translate":[{"time":0,"x":0,"y":0,"curve":"stepped"},{"time":0.1333,"x":0,"y":0,"curve":"stepped"},{"time":0.2333,"x":0,"y":0,"curve":"stepped"},{"time":0.4,"x":0,"y":0,"curve":[0.312,0.26,0.653,0.62]},{"time":0.7,"x":12.24,"y":2.42,"curve":[0.276,0,0.621,0.4]},{"time":0.9,"x":-8.22,"y":-1.14,"curve":[0.312,0.26,0.653,0.62]},{"time":1.0667,"x":-24.79,"y":-14.78,"curve":[0.276,0,0.621,0.4]},{"time":1.3333,"x":-20.08,"y":5.92,"curve":[0.25,0,0.75,1]},{"time":1.8333,"x":-24.79,"y":-14.78,"curve":[0.278,0,0.622,0.39]},{"time":2.4333,"x":-18.95,"y":12.21,"curve":[0.247,0,0.632,0.53]},{"time":2.8333,"x":-29.17,"y":-3.6,"curve":[0.38,0.53,0.746,1]},{"time":3.0667,"x":-24.79,"y":-14.78}],"scale":[{"time":0,"x":1,"y":1,"curve":"stepped"},{"time":0.1333,"x":1,"y":1,"curve":"stepped"},{"time":0.2333,"x":1,"y":1,"curve":[0.25,0,0.75,1]},{"time":0.4,"x":0.939,"y":1,"curve":[0.312,0.26,0.653,0.62]},{"time":0.7,"x":0.642,"y":0.918,"curve":[0.382,0.56,0.738,1]},{"time":0.9,"x":0.18,"y":1,"curve":[0.25,0,0.75,1]},{"time":1.0667,"x":0.642,"y":0.918,"curve":"stepped"},{"time":1.3333,"x":0.642,"y":0.918,"curve":"stepped"},{"time":1.8333,"x":0.642,"y":0.918,"curve":"stepped"},{"time":2.4333,"x":0.642,"y":0.918,"curve":"stepped"},{"time":2.8333,"x":0.642,"y":0.918,"curve":"stepped"},{"time":3.0667,"x":0.642,"y":0.918}]},"Reye":{"rotate":[{"time":0,"angle":0,"curve":"stepped"},{"time":0.1333,"angle":0,"curve":"stepped"},{"time":0.2333,"angle":0,"curve":[0.25,0,0.75,1]},{"time":0.4,"angle":0.91,"curve":[0.336,0.34,0.691,0.74]},{"time":0.7,"angle":28.34,"curve":[0.25,0,0.75,1]},{"time":0.9,"angle":3.95,"curve":[0.25,0,0.75,1]},{"time":1.0667,"angle":28.34,"curve":"stepped"},{"time":1.3333,"angle":28.34,"curve":"stepped"},{"time":1.8333,"angle":28.34,"curve":"stepped"},{"time":2.4333,"angle":28.34,"curve":"stepped"},{"time":3.0667,"angle":28.34}],"translate":[{"time":0,"x":0,"y":0,"curve":"stepped"},{"time":0.1333,"x":0,"y":0,"curve":"stepped"},{"time":0.2333,"x":0,"y":0,"curve":[0.25,0,0.75,1]},{"time":0.4,"x":-0.08,"y":-3.46,"curve":[0.312,0.26,0.653,0.62]},{"time":0.7,"x":16.88,"y":3.08,"curve":[0.276,0,0.621,0.4]},{"time":0.9,"x":-8.16,"y":-1.14,"curve":[0.312,0.26,0.653,0.62]},{"time":1.0667,"x":-20.14,"y":-14.11,"curve":[0.276,0,0.621,0.4]},{"time":1.3333,"x":-22.2,"y":7.31,"curve":[0.25,0,0.75,1]},{"time":1.8333,"x":-20.14,"y":-14.11,"curve":[0.278,0,0.622,0.39]},{"time":2.4333,"x":-21.07,"y":13.59,"curve":[0.247,0,0.632,0.53]},{"time":2.8333,"x":-27.35,"y":-2.64,"curve":[0.38,0.53,0.746,1]},{"time":3.0667,"x":-20.14,"y":-14.11}],"scale":[{"time":0,"x":1,"y":1,"curve":"stepped"},{"time":0.1333,"x":1,"y":1,"curve":"stepped"},{"time":0.2333,"x":1,"y":1,"curve":[0.25,0,0.75,1]},{"time":0.4,"x":0.695,"y":1,"curve":[0.312,0.26,0.653,0.62]},{"time":0.7,"x":0.594,"y":0.731,"curve":[0.382,0.56,0.738,1]},{"time":0.9,"x":0.14,"y":1,"curve":[0.25,0,0.75,1]},{"time":1.0667,"x":0.594,"y":0.731,"curve":"stepped"},{"time":1.3333,"x":0.594,"y":0.731,"curve":"stepped"},{"time":1.8333,"x":0.594,"y":0.731,"curve":"stepped"},{"time":2.4333,"x":0.594,"y":0.731,"curve":"stepped"},{"time":2.8333,"x":0.594,"y":0.731,"curve":"stepped"},{"time":3.0667,"x":0.594,"y":0.731}]},"Lear":{"rotate":[{"time":0,"angle":0,"curve":"stepped"},{"time":0.1333,"angle":0,"curve":"stepped"},{"time":0.2667,"angle":0,"curve":"stepped"},{"time":0.4,"angle":0,"curve":[0.281,0,0.623,0.39]},{"time":0.5667,"angle":-29.78,"curve":[0.312,0.26,0.653,0.62]},{"time":0.7667,"angle":0}],"translate":[{"time":0,"x":0,"y":0,"curve":[0.25,0,0.75,1]},{"time":0.1333,"x":-3,"y":6.24,"curve":[0.25,0,0.625,0.5]},{"time":0.2667,"x":-11.86,"y":-7.3,"curve":[0.375,0.5,0.75,1]},{"time":0.4,"x":2.71,"y":2.73,"curve":[0.281,0,0.623,0.39]},{"time":0.5667,"x":0,"y":0,"curve":[0.312,0.26,0.653,0.62]},{"time":0.7667,"x":-14.44,"y":-14.53}],"scale":[{"time":0.1333,"x":1,"y":1,"curve":"stepped"},{"time":0.2667,"x":1,"y":1,"curve":"stepped"},{"time":0.4,"x":1,"y":1,"curve":"stepped"},{"time":0.5667,"x":1,"y":1,"curve":"stepped"},{"time":0.7667,"x":1,"y":1}]},"Rear":{"rotate":[{"time":0,"angle":0,"curve":"stepped"},{"time":0.1333,"angle":0,"curve":"stepped"},{"time":0.2667,"angle":0,"curve":"stepped"},{"time":0.4,"angle":0,"curve":[0.281,0,0.623,0.39]},{"time":0.5667,"angle":4.29,"curve":[0.312,0.26,0.653,0.62]},{"time":0.7667,"angle":0}],"translate":[{"time":0,"x":0,"y":0,"curve":[0.25,0,0.75,1]},{"time":0.1333,"x":6.58,"y":2.16,"curve":[0.25,0,0.625,0.5]},{"time":0.2667,"x":-5.69,"y":12.72,"curve":[0.375,0.5,0.75,1]},{"time":0.4,"x":1.46,"y":-1.9,"curve":[0.281,0,0.623,0.39]},{"time":0.5667,"x":-3.06,"y":3.41,"curve":[0.312,0.26,0.653,0.62]},{"time":0.7667,"x":-12.52,"y":16.22}],"scale":[{"time":0.1333,"x":1,"y":1,"curve":"stepped"},{"time":0.2667,"x":1,"y":1,"curve":"stepped"},{"time":0.4,"x":1,"y":1,"curve":"stepped"},{"time":0.5667,"x":1,"y":1,"curve":"stepped"},{"time":0.7667,"x":1,"y":1}]},"xin":{"rotate":[{"time":0,"angle":0,"curve":[0.244,0,0.7,0.79]},{"time":0.8333,"angle":-12.52,"curve":[0.352,0.47,0.687,0.81]},{"time":1.4,"angle":2.7}],"translate":[{"time":0,"x":0,"y":0,"curve":[0.244,0,0.7,0.79]},{"time":0.8333,"x":-171.36,"y":60.03},{"time":1,"x":-186.15,"y":-7.28,"curve":[0.25,0,0.75,1]},{"time":1.2,"x":-253.19,"y":-45.46,"curve":[0.331,0.33,0.669,0.67]},{"time":1.4,"x":-232.28,"y":-59.17,"curve":[0.344,0.37,0.682,0.72]},{"time":1.5333,"x":-247.31,"y":-71.82,"curve":[0.25,0,0.75,1]},{"time":1.7,"x":-239.39,"y":-75.85}],"scale":[{"time":0,"x":1,"y":0,"curve":[0.244,0,0.7,0.79]},{"time":0.8333,"x":0,"y":0,"curve":[0.335,0.34,0.669,0.68]},{"time":1.2,"x":1,"y":0.91,"curve":[0.25,0,0.75,1]},{"time":1.4,"x":0.839,"y":1,"curve":[0.25,0,0.75,1]},{"time":1.5333,"x":0.966,"y":1,"curve":[0.25,0,0.75,1]},{"time":1.7,"x":1,"y":1}]},"shadow":{"rotate":[{"time":0,"angle":0,"curve":"stepped"},{"time":1.3333,"angle":0}],"translate":[{"time":0,"x":-155.57,"y":-3.5,"curve":[0.25,0,0.75,1]},{"time":0.2667,"x":-76.04,"y":-3.5,"curve":[0.25,0,0.75,1]},{"time":0.4667,"x":8.73,"y":-3.5}],"scale":[{"time":0,"x":1,"y":1,"curve":[0.25,0,0.75,1]},{"time":0.2667,"x":0.764,"y":0.589,"curve":[0.25,0,0.75,1]},{"time":0.4667,"x":1,"y":1}]},"body":{"rotate":[{"time":0,"angle":0,"curve":[0.278,0,0.622,0.4]},{"time":0.1333,"angle":12.55,"curve":[0.313,0.27,0.655,0.63]},{"time":0.4,"angle":16.13,"curve":[0.34,0.36,0.674,0.69]},{"time":0.5667,"angle":-0.35,"curve":[0.25,0,0.75,1]},{"time":0.7667,"angle":-1.98,"curve":[0.351,0.4,0.757,1]},{"time":1,"angle":-5,"curve":[0.25,0,0.75,1]},{"time":1.3333,"angle":2.2,"curve":[0.25,0,0.75,1]},{"time":1.8333,"angle":-3.84,"curve":[0.25,0,0.75,1]},{"time":2.4333,"angle":1.13,"curve":[0.25,0,0.75,1]},{"time":3.0667,"angle":-3.84}],"translate":[{"time":0,"x":0,"y":0,"curve":"stepped"},{"time":0.1333,"x":0,"y":0,"curve":[0.25,0,0.75,1]},{"time":0.4,"x":16.03,"y":1.58,"curve":[0.351,0.42,0.686,0.76]},{"time":0.5667,"x":4.98,"y":3.52,"curve":[0.36,0.64,0.695,1]},{"time":0.7667,"x":3.19,"y":0.13,"curve":"stepped"},{"time":1,"x":3.19,"y":0.13,"curve":"stepped"},{"time":1.3333,"x":3.19,"y":0.13,"curve":"stepped"},{"time":1.8333,"x":3.19,"y":0.13,"curve":"stepped"},{"time":2.4333,"x":3.19,"y":0.13,"curve":"stepped"},{"time":3.0667,"x":3.19,"y":0.13}],"scale":[{"time":0,"x":1,"y":1,"curve":"stepped"},{"time":0.1333,"x":1,"y":1,"curve":[0.25,0,0.75,1]},{"time":0.4,"x":1.062,"y":1,"curve":[0.25,0,0.625,0.5]},{"time":0.5667,"x":0.907,"y":1,"curve":[0.375,0.5,0.75,1]},{"time":0.7667,"x":1.179,"y":0.995,"curve":[0.25,0,0.75,1]},{"time":1,"x":0.933,"y":1,"curve":[0.25,0,0.75,1]},{"time":1.3333,"x":1,"y":1,"curve":"stepped"},{"time":1.8333,"x":1,"y":1,"curve":"stepped"},{"time":2.4333,"x":1,"y":1,"curve":"stepped"},{"time":3.0667,"x":1,"y":1}]},"text":{"rotate":[{"time":0,"angle":0,"curve":"stepped"},{"time":0.9,"angle":0,"curve":"stepped"},{"time":1.1,"angle":0,"curve":"stepped"},{"time":1.2333,"angle":0,"curve":"stepped"},{"time":1.4,"angle":0}],"translate":[{"time":0,"x":-116.67,"y":233.72,"curve":"stepped"},{"time":0.9,"x":-116.67,"y":233.72,"curve":[0.25,0,0.75,1]},{"time":1.1,"x":0,"y":0,"curve":"stepped"},{"time":1.2333,"x":0,"y":0,"curve":"stepped"},{"time":1.4,"x":0,"y":0}],"scale":[{"time":0,"x":0,"y":0,"curve":"stepped"},{"time":0.9,"x":0,"y":0,"curve":[0.25,0,0.75,1]},{"time":1.1,"x":1.16,"y":1.1,"curve":[0.25,0,0.75,1]},{"time":1.2333,"x":0.9,"y":0.9,"curve":[0.25,0,0.75,1]},{"time":1.4,"x":1,"y":1}]},"LIGHT":{"rotate":[{"time":0,"angle":0}],"translate":[{"time":0,"x":0,"y":0}],"scale":[{"time":0,"x":1,"y":1}]}}},"fault_1":{"slots":{"body":{"color":[{"time":0,"color":"ffffff00","curve":[0.25,0,0.75,1]},{"time":0.2333,"color":"ffffffff"}]},"close":{"attachment":[{"time":0,"name":null}]},"head":{"color":[{"time":0,"color":"ffffff00","curve":[0.25,0,0.75,1]},{"time":0.2667,"color":"ffffffff"}]},"lbi":{"color":[{"time":0,"color":"ffffff00","curve":[0.25,0,0.75,1]},{"time":0.2333,"color":"ffffffff"}]},"lear":{"color":[{"time":0,"color":"ffffff00","curve":[0.25,0,0.75,1]},{"time":0.2333,"color":"ffffffff"}]},"leye":{"color":[{"time":0,"color":"ffffff00","curve":[0.25,0,0.75,1]},{"time":0.2333,"color":"ffffffff"}]},"lfoot":{"color":[{"time":0,"color":"ffffff00","curve":[0.25,0,0.75,1]},{"time":0.2333,"color":"ffffffff"}]},"light":{"attachment":[{"time":0,"name":null}]},"light1":{"attachment":[{"time":0,"name":null}]},"light2":{"attachment":[{"time":0,"name":null}]},"light3":{"attachment":[{"time":0,"name":null}]},"light4":{"attachment":[{"time":0,"name":null}]},"light6":{"attachment":[{"time":0,"name":null}]},"light7":{"attachment":[{"time":0,"name":null}]},"lleg":{"color":[{"time":0,"color":"ffffff00","curve":[0.25,0,0.75,1]},{"time":0.2333,"color":"ffffffff"}]},"rbi":{"color":[{"time":0,"color":"ffffff00","curve":[0.25,0,0.75,1]},{"time":0.2667,"color":"ffffffff"}]},"rear":{"color":[{"time":0,"color":"ffffff00","curve":[0.25,0,0.75,1]},{"time":0.2333,"color":"ffffffff"}]},"reye":{"color":[{"time":0,"color":"ffffff00","curve":[0.25,0,0.75,1]},{"time":0.2333,"color":"ffffffff"}],"attachment":[{"time":0.2333,"name":"reye"}]},"rfoot":{"color":[{"time":0,"color":"ffffff00","curve":[0.25,0,0.75,1]},{"time":0.2333,"color":"ffffffff"}]},"rleg":{"color":[{"time":0,"color":"ffffff00","curve":[0.25,0,0.75,1]},{"time":0.2333,"color":"ffffffff"}]},"shadow":{"color":[{"time":0,"color":"ffffff00","curve":[0.25,0,0.75,1]},{"time":0.2333,"color":"ffffffff"}]},"star":{"attachment":[{"time":0,"name":null}]},"star2":{"attachment":[{"time":0,"name":null}]},"star3":{"attachment":[{"time":0,"name":null}]},"star4":{"attachment":[{"time":0,"name":null}]},"star5":{"attachment":[{"time":0,"name":null}]},"star6":{"attachment":[{"time":0,"name":null}]},"star7":{"attachment":[{"time":0,"name":null}]},"star8":{"attachment":[{"time":0,"name":null}]},"xin":{"color":[{"time":0,"color":"ffffff00","curve":[0.25,0,0.75,1]},{"time":0.8333,"color":"ffffffff"}]}},"bones":{"bodyall":{"rotate":[{"time":0,"angle":0,"curve":"stepped"},{"time":0.1333,"angle":0,"curve":"stepped"},{"time":0.2667,"angle":0,"curve":"stepped"},{"time":0.4333,"angle":0,"curve":[0.25,0,0.75,1]},{"time":0.5667,"angle":0.3,"curve":[0.272,0,0.619,0.41]},{"time":0.7667,"angle":0,"curve":"stepped"},{"time":1.0667,"angle":0}],"translate":[{"time":0,"x":-159.07,"y":-5.59,"curve":[0.276,0,0.621,0.4]},{"time":0.1333,"x":-120.8,"y":24.44,"curve":[0.314,0.27,0.657,0.64]},{"time":0.2667,"x":-73.56,"y":75.8},{"time":0.4333,"x":0,"y":0,"curve":"stepped"},{"time":0.5667,"x":0,"y":0,"curve":"stepped"},{"time":0.7667,"x":0,"y":0,"curve":"stepped"},{"time":1.0667,"x":0,"y":0}],"scale":[{"time":0.1333,"x":1,"y":1,"curve":"stepped"},{"time":0.2667,"x":1,"y":1,"curve":"stepped"},{"time":0.4333,"x":1,"y":1,"curve":"stepped"},{"time":0.5667,"x":1,"y":1,"curve":"stepped"},{"time":0.7667,"x":1,"y":1,"curve":"stepped"},{"time":1.0667,"x":1,"y":1}]},"root":{"rotate":[{"time":0,"angle":0,"curve":"stepped"},{"time":0.1333,"angle":0,"curve":"stepped"},{"time":0.2667,"angle":0,"curve":"stepped"},{"time":0.4,"angle":0,"curve":[0.281,0,0.623,0.39]},{"time":0.5667,"angle":0.3,"curve":[0.312,0.26,0.653,0.62]},{"time":0.7667,"angle":0,"curve":"stepped"},{"time":0.8333,"angle":0,"curve":"stepped"},{"time":1,"angle":0,"curve":"stepped"},{"time":1.1667,"angle":0,"curve":"stepped"},{"time":1.3333,"angle":0}],"translate":[{"time":0,"x":0,"y":0,"curve":"stepped"},{"time":0.1333,"x":0,"y":0,"curve":"stepped"},{"time":0.4,"x":0,"y":0,"curve":"stepped"},{"time":0.5667,"x":0,"y":0,"curve":"stepped"},{"time":0.7667,"x":0,"y":0,"curve":"stepped"},{"time":0.8333,"x":0,"y":0,"curve":"stepped"},{"time":1,"x":0,"y":0,"curve":"stepped"},{"time":1.1667,"x":0,"y":0}],"scale":[{"time":0.1333,"x":1,"y":1,"curve":"stepped"},{"time":0.2667,"x":1,"y":1,"curve":"stepped"},{"time":0.4,"x":1,"y":1,"curve":"stepped"},{"time":0.5667,"x":1,"y":1,"curve":"stepped"},{"time":0.7667,"x":1,"y":1,"curve":"stepped"},{"time":0.8333,"x":1,"y":1,"curve":"stepped"},{"time":1,"x":1,"y":1,"curve":"stepped"},{"time":1.1667,"x":1,"y":1}]},"lhand":{"rotate":[{"time":0,"angle":0,"curve":[0.25,0,0.75,1]},{"time":0.1333,"angle":22.72,"curve":[0.25,0,0.75,1]},{"time":0.2667,"angle":14.09,"curve":[0.254,0,0.621,0.47]},{"time":0.4,"angle":-28.39,"curve":[0.333,0.33,0.67,0.68]},{"time":0.5667,"angle":4.26,"curve":[0.344,0.37,0.681,0.71]},{"time":0.9333,"angle":-32.86,"curve":[0.379,0.6,0.724,1]},{"time":1.2,"angle":7.04,"curve":[0.381,0.55,0.742,1]},{"time":1.3333,"angle":0.92,"curve":[0.381,0.55,0.742,1]},{"time":1.8333,"angle":3.68,"curve":[0.25,0,0.75,1]},{"time":2.4333,"angle":7.04,"curve":[0.381,0.55,0.742,1]},{"time":3.0667,"angle":3.68}],"translate":[{"time":0,"x":0,"y":0,"curve":"stepped"},{"time":0.1333,"x":0,"y":0,"curve":[0.268,0,0.618,0.42]},{"time":0.2667,"x":14.96,"y":-10.18,"curve":[0.321,0.3,0.668,0.67]},{"time":0.4,"x":0,"y":0,"curve":[0.382,0.55,0.741,1]},{"time":1.2,"x":-1.87,"y":-6.8,"curve":[0.381,0.55,0.742,1]},{"time":1.3333,"x":-2.95,"y":-10.76,"curve":[0.25,0,0.75,1]},{"time":1.8333,"x":0,"y":0,"curve":[0.25,0,0.75,1]},{"time":2.4333,"x":-1.87,"y":-6.8,"curve":[0.381,0.55,0.742,1]},{"time":3.0667,"x":0,"y":0}],"scale":[{"time":0.1333,"x":1,"y":1,"curve":"stepped"},{"time":0.2667,"x":1,"y":1,"curve":"stepped"},{"time":0.4,"x":1,"y":1,"curve":"stepped"},{"time":1.3333,"x":1,"y":1,"curve":"stepped"},{"time":1.8333,"x":1,"y":1,"curve":"stepped"},{"time":2.4333,"x":1,"y":1,"curve":"stepped"},{"time":3.0667,"x":1,"y":1}]},"rhand":{"rotate":[{"time":0,"angle":-10.04,"curve":"stepped"},{"time":0.1333,"angle":-10.04,"curve":"stepped"},{"time":0.2667,"angle":-10.04,"curve":"stepped"},{"time":0.4,"angle":-10.04,"curve":[0.334,0.33,0.67,0.68]},{"time":0.5667,"angle":-34.09,"curve":[0.344,0.37,0.681,0.72]},{"time":0.9333,"angle":-15.67,"curve":[0.379,0.6,0.723,1]},{"time":1.2,"angle":-48.3,"curve":[0.381,0.55,0.742,1]},{"time":1.3333,"angle":-42.7,"curve":[0.381,0.55,0.742,1]},{"time":1.8333,"angle":-46.17,"curve":[0.25,0,0.75,1]},{"time":2.4333,"angle":-48.3,"curve":[0.381,0.55,0.742,1]},{"time":3.0667,"angle":-46.17}],"translate":[{"time":0,"x":0,"y":0,"curve":"stepped"},{"time":0.1333,"x":0,"y":0,"curve":"stepped"},{"time":0.2667,"x":0,"y":0,"curve":"stepped"},{"time":0.4,"x":0,"y":0,"curve":[0.25,0,0.625,0.5]},{"time":1.2,"x":-4.84,"y":18.43,"curve":[0.381,0.55,0.742,1]},{"time":1.3333,"x":-4.77,"y":23.27,"curve":[0.25,0,0.75,1]},{"time":1.8333,"x":-4.96,"y":10.12,"curve":[0.25,0,0.75,1]},{"time":2.4333,"x":-4.84,"y":18.43,"curve":[0.381,0.55,0.742,1]},{"time":3.0667,"x":-4.96,"y":10.12}],"scale":[{"time":0,"x":1,"y":1,"curve":"stepped"},{"time":0.1333,"x":1,"y":1,"curve":"stepped"},{"time":0.2667,"x":1,"y":1,"curve":"stepped"},{"time":0.4,"x":1,"y":1,"curve":"stepped"},{"time":1.3333,"x":1,"y":1,"curve":"stepped"},{"time":1.8333,"x":1,"y":1,"curve":"stepped"},{"time":2.4333,"x":1,"y":1,"curve":"stepped"},{"time":3.0667,"x":1,"y":1}]},"Lleg":{"rotate":[{"time":0,"angle":0,"curve":[0.25,0,0.75,1]},{"time":0.1333,"angle":0.1,"curve":[0.25,0,0.75,1]},{"time":0.2667,"angle":-31.17,"curve":[0.25,0,0.75,1]},{"time":0.4,"angle":-21.9,"curve":[0.25,0,0.75,1]},{"time":0.5,"angle":0,"curve":[0.305,0,0.64,0.36]},{"time":0.5667,"angle":0.3,"curve":[0.294,0.18,0.638,0.55]},{"time":0.7667,"angle":0}],"translate":[{"time":0,"x":0,"y":0,"curve":[0.25,0,0.75,1]},{"time":0.1333,"x":-8.93,"y":0.31,"curve":[0.25,0,0.75,1]},{"time":0.4,"x":6.36,"y":5.93,"curve":[0.25,0,0.75,1]},{"time":0.5,"x":0,"y":0,"curve":"stepped"},{"time":0.5667,"x":0,"y":0,"curve":"stepped"},{"time":0.7667,"x":0,"y":0}],"scale":[{"time":0.1333,"x":1,"y":1,"curve":"stepped"},{"time":0.2667,"x":1,"y":1,"curve":"stepped"},{"time":0.4,"x":1,"y":1,"curve":"stepped"},{"time":0.5667,"x":1,"y":1,"curve":"stepped"},{"time":0.7667,"x":1,"y":1}]},"Rleg":{"rotate":[{"time":0,"angle":0,"curve":[0.25,0,0.75,1]},{"time":0.1333,"angle":-346.42,"curve":[0.25,0,0.75,1]},{"time":0.2667,"angle":-329.28,"curve":[0.25,0,0.75,1]},{"time":0.4,"angle":-278.83,"curve":[0.25,0,0.75,1]},{"time":0.5667,"angle":0.3,"curve":[0.272,0,0.619,0.41]},{"time":0.7667,"angle":0}],"translate":[{"time":0,"x":0,"y":0,"curve":[0.25,0,0.75,1]},{"time":0.1333,"x":-8.31,"y":-1.7,"curve":[0.25,0,0.625,0.5]},{"time":0.2667,"x":13.5,"y":9.77,"curve":[0.375,0.5,0.75,1]},{"time":0.4,"x":17.77,"y":4.45,"curve":[0.25,0,0.75,1]},{"time":0.5667,"x":0,"y":0,"curve":"stepped"},{"time":0.7667,"x":0,"y":0}],"scale":[{"time":0.1333,"x":1,"y":1,"curve":"stepped"},{"time":0.2667,"x":1,"y":1,"curve":"stepped"},{"time":0.4,"x":1,"y":1,"curve":"stepped"},{"time":0.5667,"x":1,"y":1,"curve":"stepped"},{"time":0.7667,"x":1,"y":1}]},"Rfoot":{"rotate":[{"time":0,"angle":0,"curve":[0.25,0,0.75,1]},{"time":0.1333,"angle":-29.6,"curve":[0.25,0,0.75,1]},{"time":0.2667,"angle":-45.78,"curve":[0.25,0,0.75,1]},{"time":0.4,"angle":-28.13,"curve":[0.281,0,0.623,0.39]},{"time":0.5667,"angle":13.03,"curve":[0.332,0.33,0.668,0.67]},{"time":0.6333,"angle":0,"curve":"stepped"},{"time":0.7667,"angle":0,"curve":"stepped"},{"time":0.8333,"angle":0,"curve":"stepped"},{"time":1,"angle":0,"curve":"stepped"},{"time":1.1667,"angle":0,"curve":"stepped"},{"time":1.3333,"angle":0}],"translate":[{"time":0,"x":0,"y":0,"curve":[0.25,0,0.75,1]},{"time":0.1333,"x":0.49,"y":-6.26,"curve":[0.25,0,0.75,1]},{"time":0.4,"x":0.01,"y":-1.08,"curve":[0.281,0,0.623,0.39]},{"time":0.5667,"x":0,"y":0,"curve":"stepped"},{"time":0.6333,"x":0,"y":0,"curve":"stepped"},{"time":0.7667,"x":0,"y":0,"curve":"stepped"},{"time":0.8333,"x":0,"y":0,"curve":"stepped"},{"time":1,"x":0,"y":0,"curve":"stepped"},{"time":1.1667,"x":0,"y":0}],"scale":[{"time":0,"x":1,"y":1,"curve":"stepped"},{"time":0.1333,"x":1,"y":1,"curve":"stepped"},{"time":0.2667,"x":1,"y":1,"curve":"stepped"},{"time":0.4,"x":1,"y":1,"curve":"stepped"},{"time":0.5667,"x":1,"y":1,"curve":"stepped"},{"time":0.6333,"x":1,"y":1,"curve":"stepped"},{"time":0.7667,"x":1,"y":1,"curve":"stepped"},{"time":0.8333,"x":1,"y":1,"curve":"stepped"},{"time":1,"x":1,"y":1,"curve":"stepped"},{"time":1.1667,"x":1,"y":1}]},"Lfoot":{"rotate":[{"time":0,"angle":0,"curve":[0.25,0,0.75,1]},{"time":0.1333,"angle":19.02,"curve":[0.25,0,0.75,1]},{"time":0.2667,"angle":33.17,"curve":[0.25,0,0.75,1]},{"time":0.4,"angle":0,"curve":[0.281,0,0.623,0.39]},{"time":0.5667,"angle":0.3,"curve":[0.312,0.26,0.653,0.62]},{"time":0.7667,"angle":0,"curve":"stepped"},{"time":0.8333,"angle":0,"curve":"stepped"},{"time":1,"angle":0,"curve":"stepped"},{"time":1.1667,"angle":0,"curve":"stepped"},{"time":1.3333,"angle":0}],"translate":[{"time":0,"x":0,"y":0,"curve":[0.25,0,0.75,1]},{"time":0.1333,"x":-2.83,"y":-1.03,"curve":[0.25,0,0.625,0.5]},{"time":0.2667,"x":-8.72,"y":-0.16,"curve":[0.375,0.5,0.75,1]},{"time":0.4,"x":0,"y":0,"curve":"stepped"},{"time":0.5667,"x":0,"y":0,"curve":"stepped"},{"time":0.7667,"x":0,"y":0,"curve":"stepped"},{"time":0.8333,"x":0,"y":0,"curve":"stepped"},{"time":1,"x":0,"y":0,"curve":"stepped"},{"time":1.1667,"x":0,"y":0}],"scale":[{"time":0,"x":1,"y":1,"curve":"stepped"},{"time":0.1333,"x":1,"y":1,"curve":"stepped"},{"time":0.2667,"x":1,"y":1,"curve":"stepped"},{"time":0.4,"x":1,"y":1,"curve":"stepped"},{"time":0.5667,"x":1,"y":1,"curve":"stepped"},{"time":0.7667,"x":1,"y":1,"curve":"stepped"},{"time":0.8333,"x":1,"y":1,"curve":"stepped"},{"time":1,"x":1,"y":1,"curve":"stepped"},{"time":1.1667,"x":1,"y":1}]},"head":{"rotate":[{"time":0,"angle":0,"curve":[0.25,0,0.75,1]},{"time":0.1333,"angle":-8.08,"curve":[0.245,0,0.64,0.57]},{"time":0.4,"angle":5.71,"curve":[0.382,0.55,0.741,1]},{"time":0.8,"angle":-1.74,"curve":[0.382,0.56,0.74,1]},{"time":1,"angle":-7.07,"curve":[0.25,0,0.75,1]},{"time":1.3333,"angle":6.17,"curve":[0.25,0,0.75,1]},{"time":1.8333,"angle":-8.19,"curve":[0.25,0,0.75,1]},{"time":2.4333,"angle":6.17,"curve":[0.25,0,0.75,1]},{"time":3.0667,"angle":-8.19}],"translate":[{"time":0,"x":0,"y":0,"curve":[0.25,0,0.75,1]},{"time":0.1333,"x":-20.06,"y":-3.29,"curve":[0.25,0,0.625,0.5]},{"time":0.2667,"x":-26.14,"y":-5.21,"curve":[0.375,0.5,0.75,1]},{"time":0.4,"x":0,"y":0,"curve":[0.25,0,0.75,1]},{"time":0.5667,"x":-7.2,"y":4.71,"curve":[0.25,0,0.75,1]},{"time":0.8,"x":-17,"y":1.16,"curve":[0.342,0.36,0.757,1]},{"time":1,"x":-33.7,"y":0.62,"curve":[0.25,0,0.75,1]},{"time":1.3333,"x":-45.63,"y":3.38,"curve":[0.25,0,0.75,1]},{"time":1.8333,"x":-44.03,"y":-7.7,"curve":[0.25,0,0.75,1]},{"time":2.4333,"x":-45.63,"y":3.38,"curve":[0.25,0,0.75,1]},{"time":3.0667,"x":-44.03,"y":-7.7}],"scale":[{"time":0,"x":1,"y":1,"curve":"stepped"},{"time":0.1333,"x":1,"y":1,"curve":"stepped"},{"time":0.2667,"x":1,"y":1,"curve":"stepped"},{"time":0.4,"x":1,"y":1,"curve":"stepped"},{"time":0.5667,"x":1,"y":1,"curve":[0.334,0.34,0.668,0.67]},{"time":0.6333,"x":0.696,"y":1,"curve":[0.346,0.38,0.685,0.73]},{"time":0.8,"x":0.878,"y":0.913,"curve":[0.378,0.61,0.721,1]},{"time":1,"x":0.906,"y":1,"curve":[0.276,0,0.621,0.4]},{"time":1.1667,"x":1.022,"y":1,"curve":[0.314,0.27,0.657,0.64]},{"time":1.3333,"x":1,"y":1,"curve":"stepped"},{"time":1.8333,"x":1,"y":1,"curve":"stepped"},{"time":2.4333,"x":1,"y":1,"curve":"stepped"},{"time":3.0667,"x":1,"y":1}]},"Leye":{"rotate":[{"time":0,"angle":0,"curve":"stepped"},{"time":0.1333,"angle":0,"curve":"stepped"},{"time":0.2333,"angle":0,"curve":[0.25,0,0.75,1]},{"time":0.4,"angle":0.3,"curve":[0.312,0.26,0.653,0.62]},{"time":0.7,"angle":-23.2,"curve":[0.25,0,0.75,1]},{"time":0.9,"angle":-8.34,"curve":[0.25,0,0.75,1]},{"time":1.0667,"angle":-23.2,"curve":"stepped"},{"time":1.3333,"angle":-23.2,"curve":"stepped"},{"time":1.8333,"angle":-23.2,"curve":"stepped"},{"time":2.4333,"angle":-23.2,"curve":"stepped"},{"time":3.0667,"angle":-23.2}],"translate":[{"time":0,"x":0,"y":0,"curve":"stepped"},{"time":0.1333,"x":0,"y":0,"curve":"stepped"},{"time":0.2333,"x":0,"y":0,"curve":"stepped"},{"time":0.4,"x":0,"y":0,"curve":[0.312,0.26,0.653,0.62]},{"time":0.7,"x":12.24,"y":2.42,"curve":[0.276,0,0.621,0.4]},{"time":0.9,"x":-8.22,"y":-1.14,"curve":[0.312,0.26,0.653,0.62]},{"time":1.0667,"x":-24.79,"y":-14.78,"curve":[0.276,0,0.621,0.4]},{"time":1.3333,"x":-20.08,"y":5.92,"curve":[0.25,0,0.75,1]},{"time":1.8333,"x":-24.79,"y":-14.78,"curve":[0.278,0,0.622,0.39]},{"time":2.4333,"x":-18.95,"y":12.21,"curve":[0.247,0,0.632,0.53]},{"time":2.8333,"x":-29.17,"y":-3.6,"curve":[0.38,0.53,0.746,1]},{"time":3.0667,"x":-24.79,"y":-14.78}],"scale":[{"time":0,"x":1,"y":1,"curve":"stepped"},{"time":0.1333,"x":1,"y":1,"curve":"stepped"},{"time":0.2333,"x":1,"y":1,"curve":[0.25,0,0.75,1]},{"time":0.4,"x":0.939,"y":1,"curve":[0.312,0.26,0.653,0.62]},{"time":0.7,"x":0.642,"y":0.918,"curve":[0.382,0.56,0.738,1]},{"time":0.9,"x":0.18,"y":1,"curve":[0.25,0,0.75,1]},{"time":1.0667,"x":0.642,"y":0.918,"curve":"stepped"},{"time":1.3333,"x":0.642,"y":0.918,"curve":"stepped"},{"time":1.8333,"x":0.642,"y":0.918,"curve":"stepped"},{"time":2.4333,"x":0.642,"y":0.918,"curve":"stepped"},{"time":2.8333,"x":0.642,"y":0.918,"curve":"stepped"},{"time":3.0667,"x":0.642,"y":0.918}]},"Reye":{"rotate":[{"time":0,"angle":0,"curve":"stepped"},{"time":0.1333,"angle":0,"curve":"stepped"},{"time":0.2333,"angle":0,"curve":[0.25,0,0.75,1]},{"time":0.4,"angle":0.91,"curve":[0.336,0.34,0.691,0.74]},{"time":0.7,"angle":28.34,"curve":[0.25,0,0.75,1]},{"time":0.9,"angle":3.95,"curve":[0.25,0,0.75,1]},{"time":1.0667,"angle":28.34,"curve":"stepped"},{"time":1.3333,"angle":28.34,"curve":"stepped"},{"time":1.8333,"angle":28.34,"curve":"stepped"},{"time":2.4333,"angle":28.34,"curve":"stepped"},{"time":3.0667,"angle":28.34}],"translate":[{"time":0,"x":0,"y":0,"curve":"stepped"},{"time":0.1333,"x":0,"y":0,"curve":"stepped"},{"time":0.2333,"x":0,"y":0,"curve":[0.25,0,0.75,1]},{"time":0.4,"x":-0.08,"y":-3.46,"curve":[0.312,0.26,0.653,0.62]},{"time":0.7,"x":16.88,"y":3.08,"curve":[0.276,0,0.621,0.4]},{"time":0.9,"x":-8.16,"y":-1.14,"curve":[0.312,0.26,0.653,0.62]},{"time":1.0667,"x":-20.14,"y":-14.11,"curve":[0.276,0,0.621,0.4]},{"time":1.3333,"x":-22.2,"y":7.31,"curve":[0.25,0,0.75,1]},{"time":1.8333,"x":-20.14,"y":-14.11,"curve":[0.278,0,0.622,0.39]},{"time":2.4333,"x":-21.07,"y":13.59,"curve":[0.247,0,0.632,0.53]},{"time":2.8333,"x":-27.35,"y":-2.64,"curve":[0.38,0.53,0.746,1]},{"time":3.0667,"x":-20.14,"y":-14.11}],"scale":[{"time":0,"x":1,"y":1,"curve":"stepped"},{"time":0.1333,"x":1,"y":1,"curve":"stepped"},{"time":0.2333,"x":1,"y":1,"curve":[0.25,0,0.75,1]},{"time":0.4,"x":0.695,"y":1,"curve":[0.312,0.26,0.653,0.62]},{"time":0.7,"x":0.594,"y":0.731,"curve":[0.382,0.56,0.738,1]},{"time":0.9,"x":0.14,"y":1,"curve":[0.25,0,0.75,1]},{"time":1.0667,"x":0.594,"y":0.731,"curve":"stepped"},{"time":1.3333,"x":0.594,"y":0.731,"curve":"stepped"},{"time":1.8333,"x":0.594,"y":0.731,"curve":"stepped"},{"time":2.4333,"x":0.594,"y":0.731,"curve":"stepped"},{"time":2.8333,"x":0.594,"y":0.731,"curve":"stepped"},{"time":3.0667,"x":0.594,"y":0.731}]},"Lear":{"rotate":[{"time":0,"angle":0,"curve":"stepped"},{"time":0.1333,"angle":0,"curve":"stepped"},{"time":0.2667,"angle":0,"curve":"stepped"},{"time":0.4,"angle":0,"curve":[0.281,0,0.623,0.39]},{"time":0.5667,"angle":-29.78,"curve":[0.312,0.26,0.653,0.62]},{"time":0.7667,"angle":0}],"translate":[{"time":0,"x":0,"y":0,"curve":[0.25,0,0.75,1]},{"time":0.1333,"x":-3,"y":6.24,"curve":[0.25,0,0.625,0.5]},{"time":0.2667,"x":-11.86,"y":-7.3,"curve":[0.375,0.5,0.75,1]},{"time":0.4,"x":2.71,"y":2.73,"curve":[0.281,0,0.623,0.39]},{"time":0.5667,"x":0,"y":0,"curve":[0.312,0.26,0.653,0.62]},{"time":0.7667,"x":-14.44,"y":-14.53}],"scale":[{"time":0.1333,"x":1,"y":1,"curve":"stepped"},{"time":0.2667,"x":1,"y":1,"curve":"stepped"},{"time":0.4,"x":1,"y":1,"curve":"stepped"},{"time":0.5667,"x":1,"y":1,"curve":"stepped"},{"time":0.7667,"x":1,"y":1}]},"Rear":{"rotate":[{"time":0,"angle":0,"curve":"stepped"},{"time":0.1333,"angle":0,"curve":"stepped"},{"time":0.2667,"angle":0,"curve":"stepped"},{"time":0.4,"angle":0,"curve":[0.281,0,0.623,0.39]},{"time":0.5667,"angle":4.29,"curve":[0.312,0.26,0.653,0.62]},{"time":0.7667,"angle":0}],"translate":[{"time":0,"x":0,"y":0,"curve":[0.25,0,0.75,1]},{"time":0.1333,"x":6.58,"y":2.16,"curve":[0.25,0,0.625,0.5]},{"time":0.2667,"x":-5.69,"y":12.72,"curve":[0.375,0.5,0.75,1]},{"time":0.4,"x":1.46,"y":-1.9,"curve":[0.281,0,0.623,0.39]},{"time":0.5667,"x":-3.06,"y":3.41,"curve":[0.312,0.26,0.653,0.62]},{"time":0.7667,"x":-12.52,"y":16.22}],"scale":[{"time":0.1333,"x":1,"y":1,"curve":"stepped"},{"time":0.2667,"x":1,"y":1,"curve":"stepped"},{"time":0.4,"x":1,"y":1,"curve":"stepped"},{"time":0.5667,"x":1,"y":1,"curve":"stepped"},{"time":0.7667,"x":1,"y":1}]},"xin":{"rotate":[{"time":0,"angle":0,"curve":[0.244,0,0.7,0.79]},{"time":0.8333,"angle":-12.52,"curve":[0.352,0.47,0.687,0.81]},{"time":1.4,"angle":2.7}],"translate":[{"time":0,"x":0,"y":0,"curve":[0.244,0,0.7,0.79]},{"time":0.8333,"x":-171.36,"y":60.03},{"time":1,"x":-186.15,"y":-7.28,"curve":[0.25,0,0.75,1]},{"time":1.2,"x":-253.19,"y":-45.46,"curve":[0.331,0.33,0.669,0.67]},{"time":1.4,"x":-232.28,"y":-59.17,"curve":[0.344,0.37,0.682,0.72]},{"time":1.5333,"x":-247.31,"y":-71.82,"curve":[0.25,0,0.75,1]},{"time":1.7,"x":-239.39,"y":-75.85}],"scale":[{"time":0,"x":1,"y":0,"curve":[0.244,0,0.7,0.79]},{"time":0.8333,"x":0,"y":0,"curve":[0.335,0.34,0.669,0.68]},{"time":1.2,"x":1,"y":0.91,"curve":[0.25,0,0.75,1]},{"time":1.4,"x":0.839,"y":1,"curve":[0.25,0,0.75,1]},{"time":1.5333,"x":0.966,"y":1,"curve":[0.25,0,0.75,1]},{"time":1.7,"x":1,"y":1}]},"shadow":{"rotate":[{"time":0,"angle":0,"curve":"stepped"},{"time":1.3333,"angle":0}],"translate":[{"time":0,"x":-155.57,"y":-3.5,"curve":[0.25,0,0.75,1]},{"time":0.2667,"x":-76.04,"y":-3.5,"curve":[0.25,0,0.75,1]},{"time":0.4667,"x":8.73,"y":-3.5}],"scale":[{"time":0,"x":1,"y":1,"curve":[0.25,0,0.75,1]},{"time":0.2667,"x":0.764,"y":0.589,"curve":[0.25,0,0.75,1]},{"time":0.4667,"x":1,"y":1}]},"body":{"rotate":[{"time":0,"angle":0,"curve":[0.278,0,0.622,0.4]},{"time":0.1333,"angle":12.55,"curve":[0.313,0.27,0.655,0.63]},{"time":0.4,"angle":16.13,"curve":[0.34,0.36,0.674,0.69]},{"time":0.5667,"angle":-0.35,"curve":[0.25,0,0.75,1]},{"time":0.7667,"angle":-1.98,"curve":[0.351,0.4,0.757,1]},{"time":1,"angle":-5,"curve":[0.25,0,0.75,1]},{"time":1.3333,"angle":2.2,"curve":[0.25,0,0.75,1]},{"time":1.8333,"angle":-3.84,"curve":[0.25,0,0.75,1]},{"time":2.4333,"angle":1.13,"curve":[0.25,0,0.75,1]},{"time":3.0667,"angle":-3.84}],"translate":[{"time":0,"x":0,"y":0,"curve":"stepped"},{"time":0.1333,"x":0,"y":0,"curve":[0.25,0,0.75,1]},{"time":0.4,"x":16.03,"y":1.58,"curve":[0.351,0.42,0.686,0.76]},{"time":0.5667,"x":4.98,"y":3.52,"curve":[0.36,0.64,0.695,1]},{"time":0.7667,"x":3.19,"y":0.13,"curve":"stepped"},{"time":1,"x":3.19,"y":0.13,"curve":"stepped"},{"time":1.3333,"x":3.19,"y":0.13,"curve":"stepped"},{"time":1.8333,"x":3.19,"y":0.13,"curve":"stepped"},{"time":2.4333,"x":3.19,"y":0.13,"curve":"stepped"},{"time":3.0667,"x":3.19,"y":0.13}],"scale":[{"time":0,"x":1,"y":1,"curve":"stepped"},{"time":0.1333,"x":1,"y":1,"curve":[0.25,0,0.75,1]},{"time":0.4,"x":1.062,"y":1,"curve":[0.25,0,0.625,0.5]},{"time":0.5667,"x":0.907,"y":1,"curve":[0.375,0.5,0.75,1]},{"time":0.7667,"x":1.179,"y":0.995,"curve":[0.25,0,0.75,1]},{"time":1,"x":0.933,"y":1,"curve":[0.25,0,0.75,1]},{"time":1.3333,"x":1,"y":1,"curve":"stepped"},{"time":1.8333,"x":1,"y":1,"curve":"stepped"},{"time":2.4333,"x":1,"y":1,"curve":"stepped"},{"time":3.0667,"x":1,"y":1}]},"text":{"rotate":[{"time":0,"angle":0,"curve":"stepped"},{"time":0.9,"angle":0,"curve":"stepped"},{"time":1.1,"angle":0,"curve":"stepped"},{"time":1.2333,"angle":0,"curve":"stepped"},{"time":1.4,"angle":0}],"translate":[{"time":0,"x":-116.67,"y":233.72,"curve":"stepped"},{"time":0.9,"x":-116.67,"y":233.72,"curve":[0.25,0,0.75,1]},{"time":1.1,"x":0,"y":0,"curve":"stepped"},{"time":1.2333,"x":0,"y":0,"curve":"stepped"},{"time":1.4,"x":0,"y":0}],"scale":[{"time":0,"x":0,"y":0,"curve":"stepped"},{"time":0.9,"x":0,"y":0,"curve":[0.25,0,0.75,1]},{"time":1.1,"x":1.16,"y":1.1,"curve":[0.25,0,0.75,1]},{"time":1.2333,"x":0.9,"y":0.9,"curve":[0.25,0,0.75,1]},{"time":1.4,"x":1,"y":1}]},"LIGHT":{"rotate":[{"time":0,"angle":0}],"translate":[{"time":0,"x":0,"y":0}],"scale":[{"time":0,"x":1,"y":1}]}}},"right":{"slots":{"light":{"attachment":[{"time":0,"name":null}]},"light1":{"attachment":[{"time":0,"name":null}]},"light2":{"attachment":[{"time":0,"name":null}]},"light3":{"attachment":[{"time":0,"name":null}]},"light4":{"attachment":[{"time":0,"name":null}]},"light6":{"attachment":[{"time":0,"name":null}]},"light7":{"attachment":[{"time":0,"name":null}]},"star":{"attachment":[{"time":0,"name":null}]},"star2":{"attachment":[{"time":0,"name":null}]},"star3":{"attachment":[{"time":0,"name":null}]},"star4":{"attachment":[{"time":0,"name":null}]},"star5":{"attachment":[{"time":0,"name":null}]},"star6":{"attachment":[{"time":0,"name":null}]},"star7":{"attachment":[{"time":0,"name":null}]},"star8":{"attachment":[{"time":0,"name":null}]}},"bones":{"bodyall":{"rotate":[{"time":0,"angle":0,"curve":"stepped"},{"time":0.1333,"angle":0,"curve":"stepped"},{"time":0.2667,"angle":0,"curve":"stepped"},{"time":0.4333,"angle":0,"curve":[0.25,0,0.75,1]},{"time":0.5667,"angle":0.3,"curve":[0.272,0,0.619,0.41]},{"time":0.7667,"angle":0,"curve":"stepped"},{"time":0.8333,"angle":0,"curve":"stepped"},{"time":1,"angle":0,"curve":"stepped"},{"time":1.1667,"angle":0,"curve":"stepped"},{"time":1.3333,"angle":0}],"translate":[{"time":0,"x":-159.07,"y":-5.59,"curve":[0.276,0,0.621,0.4]},{"time":0.1333,"x":-120.8,"y":24.44,"curve":[0.314,0.27,0.657,0.64]},{"time":0.2667,"x":-73.56,"y":75.8},{"time":0.4333,"x":0,"y":0,"curve":"stepped"},{"time":0.5667,"x":0,"y":0,"curve":"stepped"},{"time":0.7667,"x":0,"y":0,"curve":"stepped"},{"time":0.8333,"x":0,"y":0,"curve":"stepped"},{"time":1,"x":0,"y":0,"curve":"stepped"},{"time":1.1667,"x":0,"y":0}],"scale":[{"time":0.1333,"x":1,"y":1,"curve":"stepped"},{"time":0.2667,"x":1,"y":1,"curve":"stepped"},{"time":0.4333,"x":1,"y":1,"curve":"stepped"},{"time":0.5667,"x":1,"y":1,"curve":"stepped"},{"time":0.7667,"x":1,"y":1,"curve":"stepped"},{"time":0.8333,"x":1,"y":1,"curve":"stepped"},{"time":1,"x":1,"y":1,"curve":"stepped"},{"time":1.1667,"x":1,"y":1}]},"root":{"rotate":[{"time":0,"angle":0,"curve":"stepped"},{"time":0.1333,"angle":0,"curve":"stepped"},{"time":0.2667,"angle":0,"curve":"stepped"},{"time":0.4,"angle":0,"curve":[0.281,0,0.623,0.39]},{"time":0.5667,"angle":0.3,"curve":[0.312,0.26,0.653,0.62]},{"time":0.7667,"angle":0,"curve":"stepped"},{"time":0.8333,"angle":0,"curve":"stepped"},{"time":1,"angle":0,"curve":"stepped"},{"time":1.1667,"angle":0,"curve":"stepped"},{"time":1.3333,"angle":0}],"translate":[{"time":0,"x":0,"y":0,"curve":"stepped"},{"time":0.1333,"x":0,"y":0,"curve":"stepped"},{"time":0.4,"x":0,"y":0,"curve":"stepped"},{"time":0.5667,"x":0,"y":0,"curve":"stepped"},{"time":0.7667,"x":0,"y":0,"curve":"stepped"},{"time":0.8333,"x":0,"y":0,"curve":"stepped"},{"time":1,"x":0,"y":0,"curve":"stepped"},{"time":1.1667,"x":0,"y":0}],"scale":[{"time":0.1333,"x":1,"y":1,"curve":"stepped"},{"time":0.2667,"x":1,"y":1,"curve":"stepped"},{"time":0.4,"x":1,"y":1,"curve":"stepped"},{"time":0.5667,"x":1,"y":1,"curve":"stepped"},{"time":0.7667,"x":1,"y":1,"curve":"stepped"},{"time":0.8333,"x":1,"y":1,"curve":"stepped"},{"time":1,"x":1,"y":1,"curve":"stepped"},{"time":1.1667,"x":1,"y":1}]},"lhand":{"rotate":[{"time":0,"angle":0,"curve":[0.25,0,0.75,1]},{"time":0.1333,"angle":22.72,"curve":[0.25,0,0.75,1]},{"time":0.2667,"angle":14.09,"curve":[0.254,0,0.621,0.47]},{"time":0.4,"angle":-28.39,"curve":[0.369,0.47,0.753,1]},{"time":0.5667,"angle":13.67,"curve":[0.25,0,0.75,1]},{"time":0.7667,"angle":36.42,"curve":[0.25,0,0.75,1]},{"time":0.8333,"angle":14.16,"curve":[0.25,0,0.75,1]},{"time":1,"angle":5.72,"curve":[0.243,0,0.68,0.71]},{"time":1.1667,"angle":18.95,"curve":[0.375,0.62,0.716,1]},{"time":1.3333,"angle":11.47}],"translate":[{"time":0,"x":0,"y":0,"curve":"stepped"},{"time":0.1333,"x":0,"y":0,"curve":[0.268,0,0.618,0.42]},{"time":0.2667,"x":14.96,"y":-10.18,"curve":[0.321,0.3,0.668,0.67]},{"time":0.4,"x":0,"y":0,"curve":"stepped"},{"time":0.5667,"x":0,"y":0,"curve":"stepped"},{"time":0.7667,"x":0,"y":0,"curve":"stepped"},{"time":0.8333,"x":0,"y":0,"curve":"stepped"},{"time":1,"x":0,"y":0,"curve":"stepped"},{"time":1.1667,"x":0,"y":0,"curve":"stepped"},{"time":1.3333,"x":0,"y":0}],"scale":[{"time":0.1333,"x":1,"y":1,"curve":"stepped"},{"time":0.2667,"x":1,"y":1,"curve":"stepped"},{"time":0.4,"x":1,"y":1,"curve":"stepped"},{"time":0.5667,"x":1,"y":1,"curve":"stepped"},{"time":0.7667,"x":1,"y":1,"curve":"stepped"},{"time":0.8333,"x":1,"y":1,"curve":"stepped"},{"time":1,"x":1,"y":1,"curve":"stepped"},{"time":1.1667,"x":1,"y":1,"curve":"stepped"},{"time":1.3333,"x":1,"y":1}]},"rhand":{"rotate":[{"time":0,"angle":-57.81,"curve":[0.25,0,0.75,1]},{"time":0.1333,"angle":-86.35,"curve":[0.25,0,0.75,1]},{"time":0.2667,"angle":-76.61,"curve":[0.25,0,0.75,1]},{"time":0.4,"angle":-21.84,"curve":[0.25,0,0.75,1]},{"time":0.5667,"angle":-11.2,"curve":[0.25,0,0.75,1]},{"time":0.7667,"angle":-58.54,"curve":[0.25,0,0.75,1]},{"time":0.8333,"angle":-38.3,"curve":[0.25,0,0.75,1]},{"time":0.9667,"angle":9.64,"curve":[0.25,0,0.75,1]},{"time":1.1667,"angle":-11.09,"curve":[0.25,0,0.75,1]},{"time":1.3333,"angle":1.56}],"translate":[{"time":0,"x":0,"y":0,"curve":"stepped"},{"time":0.1333,"x":0,"y":0,"curve":[0.25,0,0.625,0.5]},{"time":0.2667,"x":7.15,"y":-3.07,"curve":[0.375,0.5,0.75,1]},{"time":0.4,"x":0,"y":0,"curve":"stepped"},{"time":0.5667,"x":0,"y":0,"curve":[0.375,0.5,0.75,1]},{"time":0.7667,"x":1.38,"y":21.34,"curve":[0.25,0,0.75,1]},{"time":0.8333,"x":-4.96,"y":10.12,"curve":"stepped"},{"time":0.9667,"x":-4.96,"y":10.12,"curve":"stepped"},{"time":1.1667,"x":-4.96,"y":10.12,"curve":"stepped"},{"time":1.3333,"x":-4.96,"y":10.12}],"scale":[{"time":0,"x":1,"y":1,"curve":"stepped"},{"time":0.1333,"x":1,"y":1,"curve":"stepped"},{"time":0.2667,"x":1,"y":1,"curve":"stepped"},{"time":0.4,"x":1,"y":1,"curve":"stepped"},{"time":0.5667,"x":1,"y":1,"curve":"stepped"},{"time":0.7667,"x":1,"y":1,"curve":"stepped"},{"time":0.8333,"x":1,"y":1,"curve":"stepped"},{"time":0.9667,"x":1,"y":1,"curve":"stepped"},{"time":1.1667,"x":1,"y":1,"curve":"stepped"},{"time":1.3333,"x":1,"y":1}]},"Lleg":{"rotate":[{"time":0,"angle":0,"curve":[0.25,0,0.75,1]},{"time":0.1333,"angle":0.1,"curve":[0.25,0,0.75,1]},{"time":0.2667,"angle":-31.17,"curve":[0.25,0,0.75,1]},{"time":0.4,"angle":-21.9,"curve":[0.25,0,0.75,1]},{"time":0.5,"angle":0,"curve":[0.305,0,0.64,0.36]},{"time":0.5667,"angle":0.3,"curve":[0.294,0.18,0.638,0.55]},{"time":0.7667,"angle":0,"curve":"stepped"},{"time":0.8333,"angle":0,"curve":"stepped"},{"time":1,"angle":0,"curve":"stepped"},{"time":1.1667,"angle":0,"curve":"stepped"},{"time":1.3333,"angle":0}],"translate":[{"time":0,"x":0,"y":0,"curve":[0.25,0,0.75,1]},{"time":0.1333,"x":-8.93,"y":0.31,"curve":[0.25,0,0.75,1]},{"time":0.4,"x":6.36,"y":5.93,"curve":[0.25,0,0.75,1]},{"time":0.5,"x":0,"y":0,"curve":"stepped"},{"time":0.5667,"x":0,"y":0,"curve":"stepped"},{"time":0.7667,"x":0,"y":0,"curve":"stepped"},{"time":0.8333,"x":0,"y":0,"curve":"stepped"},{"time":1,"x":0,"y":0,"curve":"stepped"},{"time":1.1667,"x":0,"y":0}],"scale":[{"time":0.1333,"x":1,"y":1,"curve":"stepped"},{"time":0.2667,"x":1,"y":1,"curve":"stepped"},{"time":0.4,"x":1,"y":1,"curve":"stepped"},{"time":0.5667,"x":1,"y":1,"curve":"stepped"},{"time":0.7667,"x":1,"y":1,"curve":"stepped"},{"time":0.8333,"x":1,"y":1,"curve":"stepped"},{"time":1,"x":1,"y":1,"curve":"stepped"},{"time":1.1667,"x":1,"y":1}]},"Rleg":{"rotate":[{"time":0,"angle":0,"curve":[0.25,0,0.75,1]},{"time":0.1333,"angle":-346.42,"curve":[0.25,0,0.75,1]},{"time":0.2667,"angle":-329.28,"curve":[0.25,0,0.75,1]},{"time":0.4,"angle":-278.83,"curve":[0.25,0,0.75,1]},{"time":0.5667,"angle":0.3,"curve":[0.272,0,0.619,0.41]},{"time":0.7667,"angle":0,"curve":"stepped"},{"time":0.8333,"angle":0,"curve":"stepped"},{"time":1,"angle":0,"curve":"stepped"},{"time":1.1667,"angle":0,"curve":"stepped"},{"time":1.3333,"angle":0}],"translate":[{"time":0,"x":0,"y":0,"curve":[0.25,0,0.75,1]},{"time":0.1333,"x":-8.31,"y":-1.7,"curve":[0.25,0,0.625,0.5]},{"time":0.2667,"x":13.5,"y":9.77,"curve":[0.375,0.5,0.75,1]},{"time":0.4,"x":17.77,"y":4.45,"curve":[0.25,0,0.75,1]},{"time":0.5667,"x":0,"y":0,"curve":"stepped"},{"time":0.7667,"x":0,"y":0,"curve":"stepped"},{"time":0.8333,"x":0,"y":0,"curve":"stepped"},{"time":1,"x":0,"y":0,"curve":"stepped"},{"time":1.1667,"x":0,"y":0}],"scale":[{"time":0.1333,"x":1,"y":1,"curve":"stepped"},{"time":0.2667,"x":1,"y":1,"curve":"stepped"},{"time":0.4,"x":1,"y":1,"curve":"stepped"},{"time":0.5667,"x":1,"y":1,"curve":"stepped"},{"time":0.7667,"x":1,"y":1,"curve":"stepped"},{"time":0.8333,"x":1,"y":1,"curve":"stepped"},{"time":1,"x":1,"y":1,"curve":"stepped"},{"time":1.1667,"x":1,"y":1}]},"Rfoot":{"rotate":[{"time":0,"angle":0,"curve":[0.25,0,0.75,1]},{"time":0.1333,"angle":-29.6,"curve":[0.25,0,0.75,1]},{"time":0.2667,"angle":-45.78,"curve":[0.25,0,0.75,1]},{"time":0.4,"angle":-28.13,"curve":[0.281,0,0.623,0.39]},{"time":0.5667,"angle":13.03,"curve":[0.332,0.33,0.668,0.67]},{"time":0.6333,"angle":0,"curve":"stepped"},{"time":0.7667,"angle":0,"curve":"stepped"},{"time":0.8333,"angle":0,"curve":"stepped"},{"time":1,"angle":0,"curve":"stepped"},{"time":1.1667,"angle":0,"curve":"stepped"},{"time":1.3333,"angle":0}],"translate":[{"time":0,"x":0,"y":0,"curve":[0.25,0,0.75,1]},{"time":0.1333,"x":0.49,"y":-6.26,"curve":[0.25,0,0.75,1]},{"time":0.4,"x":0.01,"y":-1.08,"curve":[0.281,0,0.623,0.39]},{"time":0.5667,"x":0,"y":0,"curve":"stepped"},{"time":0.6333,"x":0,"y":0,"curve":"stepped"},{"time":0.7667,"x":0,"y":0,"curve":"stepped"},{"time":0.8333,"x":0,"y":0,"curve":"stepped"},{"time":1,"x":0,"y":0,"curve":"stepped"},{"time":1.1667,"x":0,"y":0}],"scale":[{"time":0,"x":1,"y":1,"curve":"stepped"},{"time":0.1333,"x":1,"y":1,"curve":"stepped"},{"time":0.2667,"x":1,"y":1,"curve":"stepped"},{"time":0.4,"x":1,"y":1,"curve":"stepped"},{"time":0.5667,"x":1,"y":1,"curve":"stepped"},{"time":0.6333,"x":1,"y":1,"curve":"stepped"},{"time":0.7667,"x":1,"y":1,"curve":"stepped"},{"time":0.8333,"x":1,"y":1,"curve":"stepped"},{"time":1,"x":1,"y":1,"curve":"stepped"},{"time":1.1667,"x":1,"y":1}]},"Lfoot":{"rotate":[{"time":0,"angle":0,"curve":[0.25,0,0.75,1]},{"time":0.1333,"angle":19.02,"curve":[0.25,0,0.75,1]},{"time":0.2667,"angle":33.17,"curve":[0.25,0,0.75,1]},{"time":0.4,"angle":0,"curve":[0.281,0,0.623,0.39]},{"time":0.5667,"angle":0.3,"curve":[0.312,0.26,0.653,0.62]},{"time":0.7667,"angle":0,"curve":"stepped"},{"time":0.8333,"angle":0,"curve":"stepped"},{"time":1,"angle":0,"curve":"stepped"},{"time":1.1667,"angle":0,"curve":"stepped"},{"time":1.3333,"angle":0}],"translate":[{"time":0,"x":0,"y":0,"curve":[0.25,0,0.75,1]},{"time":0.1333,"x":-2.83,"y":-1.03,"curve":[0.25,0,0.625,0.5]},{"time":0.2667,"x":-8.72,"y":-0.16,"curve":[0.375,0.5,0.75,1]},{"time":0.4,"x":0,"y":0,"curve":"stepped"},{"time":0.5667,"x":0,"y":0,"curve":"stepped"},{"time":0.7667,"x":0,"y":0,"curve":"stepped"},{"time":0.8333,"x":0,"y":0,"curve":"stepped"},{"time":1,"x":0,"y":0,"curve":"stepped"},{"time":1.1667,"x":0,"y":0}],"scale":[{"time":0,"x":1,"y":1,"curve":"stepped"},{"time":0.1333,"x":1,"y":1,"curve":"stepped"},{"time":0.2667,"x":1,"y":1,"curve":"stepped"},{"time":0.4,"x":1,"y":1,"curve":"stepped"},{"time":0.5667,"x":1,"y":1,"curve":"stepped"},{"time":0.7667,"x":1,"y":1,"curve":"stepped"},{"time":0.8333,"x":1,"y":1,"curve":"stepped"},{"time":1,"x":1,"y":1,"curve":"stepped"},{"time":1.1667,"x":1,"y":1}]},"head":{"rotate":[{"time":0,"angle":0,"curve":[0.25,0,0.75,1]},{"time":0.1333,"angle":-8.08,"curve":[0.245,0,0.64,0.57]},{"time":0.4,"angle":5.71,"curve":[0.382,0.55,0.741,1]},{"time":0.7667,"angle":-1.74,"curve":[0.382,0.56,0.74,1]},{"time":1,"angle":11.31,"curve":"stepped"},{"time":1.1,"angle":11.31,"curve":"stepped"},{"time":1.3333,"angle":11.31}],"translate":[{"time":0,"x":0,"y":0,"curve":[0.25,0,0.75,1]},{"time":0.1333,"x":-20.06,"y":-3.29,"curve":[0.25,0,0.625,0.5]},{"time":0.2667,"x":-26.14,"y":-5.21,"curve":[0.375,0.5,0.75,1]},{"time":0.4,"x":0,"y":0,"curve":[0.25,0,0.75,1]},{"time":0.5667,"x":-7.2,"y":4.71,"curve":[0.25,0,0.75,1]},{"time":0.7667,"x":-26.85,"y":-0.48,"curve":[0.25,0,0.75,1]},{"time":0.8333,"x":-14.68,"y":2.58,"curve":[0.25,0,0.75,1]},{"time":1,"x":-22.59,"y":0.59,"curve":[0.25,0,0.75,1]},{"time":1.1,"x":-21.9,"y":0.76,"curve":[0.25,0,0.75,1]},{"time":1.3333,"x":-17.09,"y":1.98}],"scale":[{"time":0,"x":1,"y":1,"curve":"stepped"},{"time":0.1333,"x":1,"y":1,"curve":"stepped"},{"time":0.2667,"x":1,"y":1,"curve":"stepped"},{"time":0.4,"x":1,"y":1,"curve":"stepped"},{"time":0.5667,"x":1,"y":1,"curve":[0.375,0.5,0.75,1]},{"time":0.7667,"x":0.862,"y":1,"curve":[0.25,0,0.75,1]},{"time":0.8333,"x":0.604,"y":1,"curve":[0.25,0,0.75,1]},{"time":1,"x":1.024,"y":1,"curve":[0.25,0,0.75,1]},{"time":1.1,"x":0.795,"y":1,"curve":[0.25,0,0.75,1]},{"time":1.3333,"x":1,"y":1,"curve":"stepped"},{"time":1.5,"x":1,"y":1}]},"Leye":{"rotate":[{"time":0,"angle":0,"curve":[0.25,0,0.75,1]},{"time":0.1333,"angle":-15.48,"curve":[0.25,0,0.75,1]},{"time":0.2333,"angle":-5.59,"curve":[0.25,0,0.75,1]},{"time":0.4,"angle":0.3,"curve":"stepped"},{"time":0.5667,"angle":0.3,"curve":[0.312,0.26,0.653,0.62]},{"time":0.7667,"angle":0,"curve":"stepped"},{"time":0.8333,"angle":0,"curve":"stepped"},{"time":1,"angle":0,"curve":"stepped"},{"time":1.1667,"angle":0,"curve":"stepped"},{"time":1.3333,"angle":0}],"translate":[{"time":0,"x":0,"y":0,"curve":[0.25,0,0.75,1]},{"time":0.2333,"x":-0.78,"y":13.68,"curve":[0.375,0.5,0.75,1]},{"time":0.4,"x":0,"y":0,"curve":[0.312,0.26,0.653,0.62]},{"time":0.5667,"x":-0.18,"y":-4.99,"curve":[0.312,0.26,0.653,0.62]},{"time":0.7667,"x":0,"y":0,"curve":"stepped"},{"time":0.8333,"x":0,"y":0,"curve":[0.347,0.38,0.688,0.74]},{"time":1,"x":1.27,"y":-3.19,"curve":[0.377,0.61,0.719,1]},{"time":1.1667,"x":-5.03,"y":-2.07,"curve":[0.25,0,0.75,1]},{"time":1.3333,"x":-0.53,"y":-3.05}],"scale":[{"time":0,"x":1,"y":1,"curve":[0.25,0,0.75,1]},{"time":0.1333,"x":0.18,"y":1,"curve":[0.25,0,0.75,1]},{"time":0.2333,"x":0.104,"y":1.509,"curve":[0.25,0,0.75,1]},{"time":0.4,"x":0.939,"y":1,"curve":"stepped"},{"time":0.5667,"x":0.939,"y":1,"curve":[0.312,0.26,0.653,0.62]},{"time":0.7667,"x":0.455,"y":1,"curve":[0.332,0.33,0.668,0.67]},{"time":0.8333,"x":0.242,"y":1,"curve":[0.347,0.38,0.688,0.74]},{"time":1,"x":0.854,"y":1,"curve":[0.377,0.61,0.719,1]},{"time":1.1667,"x":0.819,"y":1}]},"Reye":{"rotate":[{"time":0,"angle":0,"curve":[0.25,0,0.75,1]},{"time":0.1333,"angle":3.95,"curve":[0.25,0,0.75,1]},{"time":0.2333,"angle":11.26,"curve":[0.25,0,0.75,1]},{"time":0.4,"angle":0.91,"curve":"stepped"},{"time":0.5667,"angle":0.91,"curve":[0.336,0.34,0.691,0.74]},{"time":0.7667,"angle":1.46,"curve":[0.378,0.61,0.721,1]},{"time":0.8333,"angle":1.75,"curve":"stepped"},{"time":1,"angle":1.75,"curve":"stepped"},{"time":1.1667,"angle":1.75,"curve":"stepped"},{"time":1.3333,"angle":1.75}],"translate":[{"time":0,"x":0,"y":0,"curve":[0.25,0,0.75,1]},{"time":0.2333,"x":1.94,"y":-6.63,"curve":[0.375,0.5,0.75,1]},{"time":0.4,"x":-0.08,"y":-3.46,"curve":[0.312,0.26,0.653,0.62]},{"time":0.5667,"x":-0.12,"y":-4.99,"curve":[0.312,0.26,0.653,0.62]},{"time":0.7667,"x":0,"y":0,"curve":"stepped"},{"time":0.8333,"x":0,"y":0,"curve":[0.347,0.38,0.688,0.74]},{"time":1,"x":1.27,"y":-3.19,"curve":[0.377,0.61,0.719,1]},{"time":1.1667,"x":-5.03,"y":-2.07,"curve":[0.25,0,0.75,1]},{"time":1.3333,"x":-0.53,"y":-3.05}],"scale":[{"time":0,"x":1,"y":1,"curve":[0.25,0,0.75,1]},{"time":0.1333,"x":0.14,"y":1,"curve":[0.25,0,0.75,1]},{"time":0.2333,"x":0.133,"y":1.509,"curve":[0.25,0,0.75,1]},{"time":0.4,"x":0.695,"y":1,"curve":"stepped"},{"time":0.5667,"x":0.695,"y":1,"curve":[0.312,0.26,0.653,0.62]},{"time":0.7667,"x":0.749,"y":1,"curve":[0.332,0.33,0.668,0.67]},{"time":0.8333,"x":0.242,"y":1,"curve":[0.347,0.38,0.688,0.74]},{"time":1,"x":1.258,"y":1,"curve":[0.377,0.61,0.719,1]},{"time":1.1667,"x":0.868,"y":1}]},"Lear":{"rotate":[{"time":0,"angle":0,"curve":"stepped"},{"time":0.1333,"angle":0,"curve":"stepped"},{"time":0.2667,"angle":0,"curve":"stepped"},{"time":0.4,"angle":0,"curve":[0.281,0,0.623,0.39]},{"time":0.5667,"angle":-29.78,"curve":[0.312,0.26,0.653,0.62]},{"time":0.7667,"angle":0,"curve":"stepped"},{"time":0.8333,"angle":0,"curve":"stepped"},{"time":1,"angle":0,"curve":"stepped"},{"time":1.1667,"angle":0,"curve":"stepped"},{"time":1.3333,"angle":0}],"translate":[{"time":0,"x":0,"y":0,"curve":[0.25,0,0.75,1]},{"time":0.1333,"x":-3,"y":6.24,"curve":[0.25,0,0.625,0.5]},{"time":0.2667,"x":-11.86,"y":-7.3,"curve":[0.375,0.5,0.75,1]},{"time":0.4,"x":2.71,"y":2.73,"curve":[0.281,0,0.623,0.39]},{"time":0.5667,"x":0,"y":0,"curve":[0.312,0.26,0.653,0.62]},{"time":0.7667,"x":-1.83,"y":-1.84,"curve":[0.332,0.33,0.668,0.67]},{"time":0.8333,"x":-21.34,"y":-21.47,"curve":[0.347,0.38,0.688,0.74]},{"time":1,"x":3.02,"y":3.03,"curve":[0.377,0.61,0.719,1]},{"time":1.1667,"x":-14.44,"y":-14.53,"curve":[0.25,0,0.75,1]},{"time":1.3333,"x":-3.72,"y":-3.75,"curve":[0.25,0,0.75,1]},{"time":1.4333,"x":-0.96,"y":-0.96}],"scale":[{"time":0.1333,"x":1,"y":1,"curve":"stepped"},{"time":0.2667,"x":1,"y":1,"curve":"stepped"},{"time":0.4,"x":1,"y":1,"curve":"stepped"},{"time":0.5667,"x":1,"y":1,"curve":"stepped"},{"time":0.7667,"x":1,"y":1,"curve":"stepped"},{"time":0.8333,"x":1,"y":1,"curve":"stepped"},{"time":1,"x":1,"y":1,"curve":"stepped"},{"time":1.1667,"x":1,"y":1}]},"Rear":{"rotate":[{"time":0,"angle":0,"curve":"stepped"},{"time":0.1333,"angle":0,"curve":"stepped"},{"time":0.2667,"angle":0,"curve":"stepped"},{"time":0.4,"angle":0,"curve":[0.281,0,0.623,0.39]},{"time":0.5667,"angle":4.29,"curve":[0.312,0.26,0.653,0.62]},{"time":0.7667,"angle":0,"curve":"stepped"},{"time":0.8333,"angle":0,"curve":"stepped"},{"time":1,"angle":0,"curve":"stepped"},{"time":1.1667,"angle":0,"curve":"stepped"},{"time":1.3333,"angle":0}],"translate":[{"time":0,"x":0,"y":0,"curve":[0.25,0,0.75,1]},{"time":0.1333,"x":6.58,"y":2.16,"curve":[0.25,0,0.625,0.5]},{"time":0.2667,"x":-5.69,"y":12.72,"curve":[0.375,0.5,0.75,1]},{"time":0.4,"x":1.46,"y":-1.9,"curve":[0.281,0,0.623,0.39]},{"time":0.5667,"x":-3.06,"y":3.41,"curve":[0.312,0.26,0.653,0.62]},{"time":0.7667,"x":-1.58,"y":2.05,"curve":[0.332,0.33,0.668,0.67]},{"time":0.8333,"x":-18.49,"y":23.96,"curve":[0.347,0.38,0.688,0.74]},{"time":1,"x":2.61,"y":-3.39,"curve":[0.377,0.61,0.719,1]},{"time":1.1667,"x":-12.52,"y":16.22,"curve":[0.25,0,0.75,1]},{"time":1.3333,"x":-3.23,"y":4.18,"curve":[0.25,0,0.75,1]},{"time":1.4333,"x":-1.47,"y":1.91}],"scale":[{"time":0.1333,"x":1,"y":1,"curve":"stepped"},{"time":0.2667,"x":1,"y":1,"curve":"stepped"},{"time":0.4,"x":1,"y":1,"curve":"stepped"},{"time":0.5667,"x":1,"y":1,"curve":"stepped"},{"time":0.7667,"x":1,"y":1,"curve":"stepped"},{"time":0.8333,"x":1,"y":1,"curve":"stepped"},{"time":1,"x":1,"y":1,"curve":"stepped"},{"time":1.1667,"x":1,"y":1}]},"xin":{"rotate":[{"time":0,"angle":0,"curve":[0.244,0,0.7,0.79]},{"time":0.8333,"angle":-12.52,"curve":[0.352,0.47,0.687,0.81]},{"time":1,"angle":-12.49,"curve":[0.348,0.66,0.682,1]},{"time":1.1,"angle":0,"curve":"stepped"},{"time":1.2,"angle":0,"curve":"stepped"},{"time":1.3333,"angle":0,"curve":"stepped"},{"time":1.4333,"angle":0,"curve":"stepped"},{"time":1.7,"angle":0}],"translate":[{"time":0,"x":0,"y":0,"curve":[0.244,0,0.7,0.79]},{"time":0.8333,"x":-171.36,"y":60.03,"curve":[0.345,0.4,0.678,0.74]},{"time":1,"x":-76.9,"y":17.23,"curve":[0.341,0.41,0.675,0.74]},{"time":1.1,"x":-13.33,"y":0.63,"curve":[0.25,0,0.75,1]},{"time":1.7,"x":0,"y":0}],"scale":[{"time":0,"x":1,"y":0,"curve":"stepped"},{"time":0.8333,"x":1,"y":0,"curve":[0.345,0.4,0.678,0.74]},{"time":1,"x":1,"y":0.445,"curve":[0.341,0.41,0.675,0.74]},{"time":1.1,"x":1,"y":1,"curve":[0.25,0,0.75,1]},{"time":1.2,"x":1,"y":0,"curve":[0.366,0.63,0.703,1]},{"time":1.3333,"x":1,"y":1,"curve":[0.25,0,0.75,1]},{"time":1.4333,"x":1,"y":0,"curve":[0.366,0.63,0.703,1]},{"time":1.7,"x":1,"y":1}]},"shadow":{"rotate":[{"time":0,"angle":0,"curve":"stepped"},{"time":1.3333,"angle":0}],"translate":[{"time":0,"x":-155.57,"y":-3.5,"curve":[0.25,0,0.75,1]},{"time":0.2667,"x":-76.04,"y":-3.5,"curve":[0.25,0,0.75,1]},{"time":0.4667,"x":8.73,"y":-3.5}],"scale":[{"time":0,"x":1,"y":1,"curve":[0.25,0,0.75,1]},{"time":0.2667,"x":0.764,"y":0.589,"curve":[0.25,0,0.75,1]},{"time":0.4667,"x":1,"y":1}]},"body":{"rotate":[{"time":0,"angle":0,"curve":[0.278,0,0.622,0.4]},{"time":0.1333,"angle":12.55,"curve":[0.313,0.27,0.655,0.63]},{"time":0.4,"angle":16.13,"curve":[0.34,0.36,0.674,0.69]},{"time":0.5667,"angle":-0.35,"curve":[0.25,0,0.75,1]},{"time":0.7667,"angle":-7.96,"curve":[0.25,0,0.75,1]},{"time":0.8333,"angle":0.35,"curve":[0.25,0,0.625,0.5]},{"time":1,"angle":-4.48,"curve":[0.375,0.5,0.75,1]},{"time":1.1667,"angle":-1.98,"curve":"stepped"},{"time":1.3333,"angle":-1.98,"curve":"stepped"},{"time":1.5,"angle":-1.98}],"translate":[{"time":0,"x":0,"y":0,"curve":"stepped"},{"time":0.1333,"x":0,"y":0,"curve":[0.25,0,0.75,1]},{"time":0.4,"x":16.03,"y":1.58,"curve":[0.351,0.42,0.686,0.76]},{"time":0.5667,"x":4.98,"y":3.52,"curve":[0.36,0.64,0.695,1]},{"time":0.7667,"x":-2.16,"y":1.44,"curve":[0.279,0,0.622,0.39]},{"time":0.8333,"x":6.9,"y":-0.11,"curve":"stepped"},{"time":1,"x":6.9,"y":-0.11,"curve":[0.382,0.55,0.741,1]},{"time":1.1667,"x":3.19,"y":0.13,"curve":[0.25,0,0.75,1]},{"time":1.3333,"x":6.9,"y":-0.11,"curve":"stepped"},{"time":1.5,"x":6.9,"y":-0.11}],"scale":[{"time":0,"x":1,"y":1,"curve":"stepped"},{"time":0.1333,"x":1,"y":1,"curve":[0.25,0,0.75,1]},{"time":0.4,"x":1.062,"y":1,"curve":[0.25,0,0.625,0.5]},{"time":0.5667,"x":0.907,"y":1,"curve":[0.375,0.5,0.75,1]},{"time":0.7667,"x":0.748,"y":1,"curve":[0.279,0,0.622,0.39]},{"time":0.8333,"x":1.121,"y":1,"curve":[0.309,0.26,0.664,0.66]},{"time":1,"x":1.06,"y":1,"curve":"stepped"},{"time":1.1667,"x":1.06,"y":1,"curve":[0.25,0,0.625,0.5]},{"time":1.3333,"x":1.03,"y":1,"curve":[0.375,0.5,0.75,1]},{"time":1.5,"x":1,"y":1}]},"text":{"rotate":[{"time":0,"angle":0,"curve":"stepped"},{"time":0.9,"angle":0,"curve":"stepped"},{"time":1.1,"angle":0,"curve":"stepped"},{"time":1.2333,"angle":0,"curve":"stepped"},{"time":1.4,"angle":0}],"translate":[{"time":0,"x":-116.67,"y":233.72,"curve":"stepped"},{"time":0.9,"x":-116.67,"y":233.72,"curve":[0.25,0,0.75,1]},{"time":1.1,"x":0,"y":0,"curve":"stepped"},{"time":1.2333,"x":0,"y":0,"curve":"stepped"},{"time":1.4,"x":0,"y":0}],"scale":[{"time":0,"x":0,"y":0,"curve":"stepped"},{"time":0.9,"x":0,"y":0,"curve":[0.25,0,0.75,1]},{"time":1.1,"x":1.16,"y":1.1,"curve":[0.25,0,0.75,1]},{"time":1.2333,"x":0.9,"y":0.9,"curve":[0.25,0,0.75,1]},{"time":1.4,"x":1,"y":1}]},"LIGHT":{"rotate":[{"time":0,"angle":0}],"translate":[{"time":0,"x":0,"y":0}],"scale":[{"time":0,"x":1,"y":1}]}}},"right_1":{"slots":{"close":{"attachment":[{"time":0,"name":null}]},"light":{"attachment":[{"time":0,"name":null}]},"light1":{"attachment":[{"time":0,"name":null}]},"light2":{"attachment":[{"time":0,"name":null}]},"light3":{"attachment":[{"time":0,"name":null}]},"light4":{"attachment":[{"time":0,"name":null}]},"light6":{"attachment":[{"time":0,"name":null}]},"light7":{"attachment":[{"time":0,"name":null}]},"star":{"attachment":[{"time":0,"name":null}]},"star2":{"attachment":[{"time":0,"name":null}]},"star3":{"attachment":[{"time":0,"name":null}]},"star4":{"attachment":[{"time":0,"name":null}]},"star5":{"attachment":[{"time":0,"name":null}]},"star6":{"attachment":[{"time":0,"name":null}]},"star7":{"attachment":[{"time":0,"name":null}]},"star8":{"attachment":[{"time":0,"name":null}]}},"bones":{"bodyall":{"rotate":[{"time":0,"angle":0,"curve":"stepped"},{"time":0.1333,"angle":0,"curve":"stepped"},{"time":0.2667,"angle":0,"curve":"stepped"},{"time":0.4333,"angle":0,"curve":[0.25,0,0.75,1]},{"time":0.5667,"angle":0.3,"curve":[0.272,0,0.619,0.41]},{"time":0.7667,"angle":0,"curve":"stepped"},{"time":0.8333,"angle":0,"curve":"stepped"},{"time":1,"angle":0,"curve":"stepped"},{"time":1.1667,"angle":0,"curve":"stepped"},{"time":1.3333,"angle":0}],"translate":[{"time":0,"x":-159.07,"y":-5.59,"curve":[0.276,0,0.621,0.4]},{"time":0.1333,"x":-120.8,"y":24.44,"curve":[0.314,0.27,0.657,0.64]},{"time":0.2667,"x":-73.56,"y":75.8},{"time":0.4333,"x":0,"y":0,"curve":"stepped"},{"time":0.5667,"x":0,"y":0,"curve":"stepped"},{"time":0.7667,"x":0,"y":0,"curve":"stepped"},{"time":0.8333,"x":0,"y":0,"curve":"stepped"},{"time":1,"x":0,"y":0,"curve":"stepped"},{"time":1.1667,"x":0,"y":0}],"scale":[{"time":0.1333,"x":1,"y":1,"curve":"stepped"},{"time":0.2667,"x":1,"y":1,"curve":"stepped"},{"time":0.4333,"x":1,"y":1,"curve":"stepped"},{"time":0.5667,"x":1,"y":1,"curve":"stepped"},{"time":0.7667,"x":1,"y":1,"curve":"stepped"},{"time":0.8333,"x":1,"y":1,"curve":"stepped"},{"time":1,"x":1,"y":1,"curve":"stepped"},{"time":1.1667,"x":1,"y":1}]},"root":{"rotate":[{"time":0,"angle":0,"curve":"stepped"},{"time":0.1333,"angle":0,"curve":"stepped"},{"time":0.2667,"angle":0,"curve":"stepped"},{"time":0.4,"angle":0,"curve":[0.281,0,0.623,0.39]},{"time":0.5667,"angle":0.3,"curve":[0.312,0.26,0.653,0.62]},{"time":0.7667,"angle":0,"curve":"stepped"},{"time":0.8333,"angle":0,"curve":"stepped"},{"time":1,"angle":0,"curve":"stepped"},{"time":1.1667,"angle":0,"curve":"stepped"},{"time":1.3333,"angle":0}],"translate":[{"time":0,"x":0,"y":0,"curve":"stepped"},{"time":0.1333,"x":0,"y":0,"curve":"stepped"},{"time":0.4,"x":0,"y":0,"curve":"stepped"},{"time":0.5667,"x":0,"y":0,"curve":"stepped"},{"time":0.7667,"x":0,"y":0,"curve":"stepped"},{"time":0.8333,"x":0,"y":0,"curve":"stepped"},{"time":1,"x":0,"y":0,"curve":"stepped"},{"time":1.1667,"x":0,"y":0}],"scale":[{"time":0.1333,"x":1,"y":1,"curve":"stepped"},{"time":0.2667,"x":1,"y":1,"curve":"stepped"},{"time":0.4,"x":1,"y":1,"curve":"stepped"},{"time":0.5667,"x":1,"y":1,"curve":"stepped"},{"time":0.7667,"x":1,"y":1,"curve":"stepped"},{"time":0.8333,"x":1,"y":1,"curve":"stepped"},{"time":1,"x":1,"y":1,"curve":"stepped"},{"time":1.1667,"x":1,"y":1}]},"lhand":{"rotate":[{"time":0,"angle":0,"curve":[0.25,0,0.75,1]},{"time":0.1333,"angle":22.72,"curve":[0.25,0,0.75,1]},{"time":0.2667,"angle":14.09,"curve":[0.254,0,0.621,0.47]},{"time":0.4,"angle":-28.39,"curve":[0.369,0.47,0.753,1]},{"time":0.5667,"angle":13.67,"curve":[0.25,0,0.75,1]},{"time":0.7667,"angle":36.42,"curve":[0.25,0,0.75,1]},{"time":0.8333,"angle":14.16,"curve":[0.25,0,0.75,1]},{"time":1,"angle":5.72,"curve":[0.243,0,0.68,0.71]},{"time":1.1667,"angle":18.95,"curve":[0.375,0.62,0.716,1]},{"time":1.3333,"angle":11.47}],"translate":[{"time":0,"x":0,"y":0,"curve":"stepped"},{"time":0.1333,"x":0,"y":0,"curve":[0.268,0,0.618,0.42]},{"time":0.2667,"x":14.96,"y":-10.18,"curve":[0.321,0.3,0.668,0.67]},{"time":0.4,"x":0,"y":0,"curve":"stepped"},{"time":0.5667,"x":0,"y":0,"curve":"stepped"},{"time":0.7667,"x":0,"y":0,"curve":"stepped"},{"time":0.8333,"x":0,"y":0,"curve":"stepped"},{"time":1,"x":0,"y":0,"curve":"stepped"},{"time":1.1667,"x":0,"y":0,"curve":"stepped"},{"time":1.3333,"x":0,"y":0}],"scale":[{"time":0.1333,"x":1,"y":1,"curve":"stepped"},{"time":0.2667,"x":1,"y":1,"curve":"stepped"},{"time":0.4,"x":1,"y":1,"curve":"stepped"},{"time":0.5667,"x":1,"y":1,"curve":"stepped"},{"time":0.7667,"x":1,"y":1,"curve":"stepped"},{"time":0.8333,"x":1,"y":1,"curve":"stepped"},{"time":1,"x":1,"y":1,"curve":"stepped"},{"time":1.1667,"x":1,"y":1,"curve":"stepped"},{"time":1.3333,"x":1,"y":1}]},"rhand":{"rotate":[{"time":0,"angle":-57.81,"curve":[0.25,0,0.75,1]},{"time":0.1333,"angle":-86.35,"curve":[0.25,0,0.75,1]},{"time":0.2667,"angle":-76.61,"curve":[0.25,0,0.75,1]},{"time":0.4,"angle":-21.84,"curve":[0.25,0,0.75,1]},{"time":0.5667,"angle":-11.2,"curve":[0.25,0,0.75,1]},{"time":0.7667,"angle":-58.54,"curve":[0.25,0,0.75,1]},{"time":0.8333,"angle":-38.3,"curve":[0.25,0,0.75,1]},{"time":0.9667,"angle":9.64,"curve":[0.25,0,0.75,1]},{"time":1.1667,"angle":-11.09,"curve":[0.25,0,0.75,1]},{"time":1.3333,"angle":1.56}],"translate":[{"time":0,"x":0,"y":0,"curve":"stepped"},{"time":0.1333,"x":0,"y":0,"curve":[0.25,0,0.625,0.5]},{"time":0.2667,"x":7.15,"y":-3.07,"curve":[0.375,0.5,0.75,1]},{"time":0.4,"x":0,"y":0,"curve":"stepped"},{"time":0.5667,"x":0,"y":0,"curve":[0.375,0.5,0.75,1]},{"time":0.7667,"x":1.38,"y":21.34,"curve":[0.25,0,0.75,1]},{"time":0.8333,"x":-4.96,"y":10.12,"curve":"stepped"},{"time":0.9667,"x":-4.96,"y":10.12,"curve":"stepped"},{"time":1.1667,"x":-4.96,"y":10.12,"curve":"stepped"},{"time":1.3333,"x":-4.96,"y":10.12}],"scale":[{"time":0,"x":1,"y":1,"curve":"stepped"},{"time":0.1333,"x":1,"y":1,"curve":"stepped"},{"time":0.2667,"x":1,"y":1,"curve":"stepped"},{"time":0.4,"x":1,"y":1,"curve":"stepped"},{"time":0.5667,"x":1,"y":1,"curve":"stepped"},{"time":0.7667,"x":1,"y":1,"curve":"stepped"},{"time":0.8333,"x":1,"y":1,"curve":"stepped"},{"time":0.9667,"x":1,"y":1,"curve":"stepped"},{"time":1.1667,"x":1,"y":1,"curve":"stepped"},{"time":1.3333,"x":1,"y":1}]},"Lleg":{"rotate":[{"time":0,"angle":0,"curve":[0.25,0,0.75,1]},{"time":0.1333,"angle":0.1,"curve":[0.25,0,0.75,1]},{"time":0.2667,"angle":-31.17,"curve":[0.25,0,0.75,1]},{"time":0.4,"angle":-21.9,"curve":[0.25,0,0.75,1]},{"time":0.5,"angle":0,"curve":[0.305,0,0.64,0.36]},{"time":0.5667,"angle":0.3,"curve":[0.294,0.18,0.638,0.55]},{"time":0.7667,"angle":0,"curve":"stepped"},{"time":0.8333,"angle":0,"curve":"stepped"},{"time":1,"angle":0,"curve":"stepped"},{"time":1.1667,"angle":0,"curve":"stepped"},{"time":1.3333,"angle":0}],"translate":[{"time":0,"x":0,"y":0,"curve":[0.25,0,0.75,1]},{"time":0.1333,"x":-8.93,"y":0.31,"curve":[0.25,0,0.75,1]},{"time":0.4,"x":6.36,"y":5.93,"curve":[0.25,0,0.75,1]},{"time":0.5,"x":0,"y":0,"curve":"stepped"},{"time":0.5667,"x":0,"y":0,"curve":"stepped"},{"time":0.7667,"x":0,"y":0,"curve":"stepped"},{"time":0.8333,"x":0,"y":0,"curve":"stepped"},{"time":1,"x":0,"y":0,"curve":"stepped"},{"time":1.1667,"x":0,"y":0}],"scale":[{"time":0.1333,"x":1,"y":1,"curve":"stepped"},{"time":0.2667,"x":1,"y":1,"curve":"stepped"},{"time":0.4,"x":1,"y":1,"curve":"stepped"},{"time":0.5667,"x":1,"y":1,"curve":"stepped"},{"time":0.7667,"x":1,"y":1,"curve":"stepped"},{"time":0.8333,"x":1,"y":1,"curve":"stepped"},{"time":1,"x":1,"y":1,"curve":"stepped"},{"time":1.1667,"x":1,"y":1}]},"Rleg":{"rotate":[{"time":0,"angle":0,"curve":[0.25,0,0.75,1]},{"time":0.1333,"angle":-346.42,"curve":[0.25,0,0.75,1]},{"time":0.2667,"angle":-329.28,"curve":[0.25,0,0.75,1]},{"time":0.4,"angle":-278.83,"curve":[0.25,0,0.75,1]},{"time":0.5667,"angle":0.3,"curve":[0.272,0,0.619,0.41]},{"time":0.7667,"angle":0,"curve":"stepped"},{"time":0.8333,"angle":0,"curve":"stepped"},{"time":1,"angle":0,"curve":"stepped"},{"time":1.1667,"angle":0,"curve":"stepped"},{"time":1.3333,"angle":0}],"translate":[{"time":0,"x":0,"y":0,"curve":[0.25,0,0.75,1]},{"time":0.1333,"x":-8.31,"y":-1.7,"curve":[0.25,0,0.625,0.5]},{"time":0.2667,"x":13.5,"y":9.77,"curve":[0.375,0.5,0.75,1]},{"time":0.4,"x":17.77,"y":4.45,"curve":[0.25,0,0.75,1]},{"time":0.5667,"x":0,"y":0,"curve":"stepped"},{"time":0.7667,"x":0,"y":0,"curve":"stepped"},{"time":0.8333,"x":0,"y":0,"curve":"stepped"},{"time":1,"x":0,"y":0,"curve":"stepped"},{"time":1.1667,"x":0,"y":0}],"scale":[{"time":0.1333,"x":1,"y":1,"curve":"stepped"},{"time":0.2667,"x":1,"y":1,"curve":"stepped"},{"time":0.4,"x":1,"y":1,"curve":"stepped"},{"time":0.5667,"x":1,"y":1,"curve":"stepped"},{"time":0.7667,"x":1,"y":1,"curve":"stepped"},{"time":0.8333,"x":1,"y":1,"curve":"stepped"},{"time":1,"x":1,"y":1,"curve":"stepped"},{"time":1.1667,"x":1,"y":1}]},"Rfoot":{"rotate":[{"time":0,"angle":0,"curve":[0.25,0,0.75,1]},{"time":0.1333,"angle":-29.6,"curve":[0.25,0,0.75,1]},{"time":0.2667,"angle":-45.78,"curve":[0.25,0,0.75,1]},{"time":0.4,"angle":-28.13,"curve":[0.281,0,0.623,0.39]},{"time":0.5667,"angle":13.03,"curve":[0.332,0.33,0.668,0.67]},{"time":0.6333,"angle":0,"curve":"stepped"},{"time":0.7667,"angle":0,"curve":"stepped"},{"time":0.8333,"angle":0,"curve":"stepped"},{"time":1,"angle":0,"curve":"stepped"},{"time":1.1667,"angle":0,"curve":"stepped"},{"time":1.3333,"angle":0}],"translate":[{"time":0,"x":0,"y":0,"curve":[0.25,0,0.75,1]},{"time":0.1333,"x":0.49,"y":-6.26,"curve":[0.25,0,0.75,1]},{"time":0.4,"x":0.01,"y":-1.08,"curve":[0.281,0,0.623,0.39]},{"time":0.5667,"x":0,"y":0,"curve":"stepped"},{"time":0.6333,"x":0,"y":0,"curve":"stepped"},{"time":0.7667,"x":0,"y":0,"curve":"stepped"},{"time":0.8333,"x":0,"y":0,"curve":"stepped"},{"time":1,"x":0,"y":0,"curve":"stepped"},{"time":1.1667,"x":0,"y":0}],"scale":[{"time":0,"x":1,"y":1,"curve":"stepped"},{"time":0.1333,"x":1,"y":1,"curve":"stepped"},{"time":0.2667,"x":1,"y":1,"curve":"stepped"},{"time":0.4,"x":1,"y":1,"curve":"stepped"},{"time":0.5667,"x":1,"y":1,"curve":"stepped"},{"time":0.6333,"x":1,"y":1,"curve":"stepped"},{"time":0.7667,"x":1,"y":1,"curve":"stepped"},{"time":0.8333,"x":1,"y":1,"curve":"stepped"},{"time":1,"x":1,"y":1,"curve":"stepped"},{"time":1.1667,"x":1,"y":1}]},"Lfoot":{"rotate":[{"time":0,"angle":0,"curve":[0.25,0,0.75,1]},{"time":0.1333,"angle":19.02,"curve":[0.25,0,0.75,1]},{"time":0.2667,"angle":33.17,"curve":[0.25,0,0.75,1]},{"time":0.4,"angle":0,"curve":[0.281,0,0.623,0.39]},{"time":0.5667,"angle":0.3,"curve":[0.312,0.26,0.653,0.62]},{"time":0.7667,"angle":0,"curve":"stepped"},{"time":0.8333,"angle":0,"curve":"stepped"},{"time":1,"angle":0,"curve":"stepped"},{"time":1.1667,"angle":0,"curve":"stepped"},{"time":1.3333,"angle":0}],"translate":[{"time":0,"x":0,"y":0,"curve":[0.25,0,0.75,1]},{"time":0.1333,"x":-2.83,"y":-1.03,"curve":[0.25,0,0.625,0.5]},{"time":0.2667,"x":-8.72,"y":-0.16,"curve":[0.375,0.5,0.75,1]},{"time":0.4,"x":0,"y":0,"curve":"stepped"},{"time":0.5667,"x":0,"y":0,"curve":"stepped"},{"time":0.7667,"x":0,"y":0,"curve":"stepped"},{"time":0.8333,"x":0,"y":0,"curve":"stepped"},{"time":1,"x":0,"y":0,"curve":"stepped"},{"time":1.1667,"x":0,"y":0}],"scale":[{"time":0,"x":1,"y":1,"curve":"stepped"},{"time":0.1333,"x":1,"y":1,"curve":"stepped"},{"time":0.2667,"x":1,"y":1,"curve":"stepped"},{"time":0.4,"x":1,"y":1,"curve":"stepped"},{"time":0.5667,"x":1,"y":1,"curve":"stepped"},{"time":0.7667,"x":1,"y":1,"curve":"stepped"},{"time":0.8333,"x":1,"y":1,"curve":"stepped"},{"time":1,"x":1,"y":1,"curve":"stepped"},{"time":1.1667,"x":1,"y":1}]},"head":{"rotate":[{"time":0,"angle":0,"curve":[0.25,0,0.75,1]},{"time":0.1333,"angle":-8.08,"curve":[0.245,0,0.64,0.57]},{"time":0.4,"angle":5.71,"curve":[0.382,0.55,0.741,1]},{"time":0.7667,"angle":-1.74,"curve":[0.382,0.56,0.74,1]},{"time":1,"angle":11.31,"curve":"stepped"},{"time":1.1,"angle":11.31,"curve":"stepped"},{"time":1.3333,"angle":11.31}],"translate":[{"time":0,"x":0,"y":0,"curve":[0.25,0,0.75,1]},{"time":0.1333,"x":-20.06,"y":-3.29,"curve":[0.25,0,0.625,0.5]},{"time":0.2667,"x":-26.14,"y":-5.21,"curve":[0.375,0.5,0.75,1]},{"time":0.4,"x":0,"y":0,"curve":[0.25,0,0.75,1]},{"time":0.5667,"x":-7.2,"y":4.71,"curve":[0.25,0,0.75,1]},{"time":0.7667,"x":-26.85,"y":-0.48,"curve":[0.25,0,0.75,1]},{"time":0.8333,"x":-14.68,"y":2.58,"curve":[0.25,0,0.75,1]},{"time":1,"x":-22.59,"y":0.59,"curve":[0.25,0,0.75,1]},{"time":1.1,"x":-21.9,"y":0.76,"curve":[0.25,0,0.75,1]},{"time":1.3333,"x":-17.09,"y":1.98}],"scale":[{"time":0,"x":1,"y":1,"curve":"stepped"},{"time":0.1333,"x":1,"y":1,"curve":"stepped"},{"time":0.2667,"x":1,"y":1,"curve":"stepped"},{"time":0.4,"x":1,"y":1,"curve":"stepped"},{"time":0.5667,"x":1,"y":1,"curve":[0.375,0.5,0.75,1]},{"time":0.7667,"x":0.862,"y":1,"curve":[0.25,0,0.75,1]},{"time":0.8333,"x":0.604,"y":1,"curve":[0.25,0,0.75,1]},{"time":1,"x":1.024,"y":1,"curve":[0.25,0,0.75,1]},{"time":1.1,"x":0.795,"y":1,"curve":[0.25,0,0.75,1]},{"time":1.3333,"x":1,"y":1,"curve":"stepped"},{"time":1.5,"x":1,"y":1}]},"Leye":{"rotate":[{"time":0,"angle":0,"curve":[0.25,0,0.75,1]},{"time":0.1333,"angle":-15.48,"curve":[0.25,0,0.75,1]},{"time":0.2333,"angle":-5.59,"curve":[0.25,0,0.75,1]},{"time":0.4,"angle":0.3,"curve":"stepped"},{"time":0.5667,"angle":0.3,"curve":[0.312,0.26,0.653,0.62]},{"time":0.7667,"angle":0,"curve":"stepped"},{"time":0.8333,"angle":0,"curve":"stepped"},{"time":1,"angle":0,"curve":"stepped"},{"time":1.1667,"angle":0,"curve":"stepped"},{"time":1.3333,"angle":0}],"translate":[{"time":0,"x":0,"y":0,"curve":[0.25,0,0.75,1]},{"time":0.2333,"x":-0.78,"y":13.68,"curve":[0.375,0.5,0.75,1]},{"time":0.4,"x":0,"y":0,"curve":[0.312,0.26,0.653,0.62]},{"time":0.5667,"x":-0.18,"y":-4.99,"curve":[0.312,0.26,0.653,0.62]},{"time":0.7667,"x":0,"y":0,"curve":"stepped"},{"time":0.8333,"x":0,"y":0,"curve":[0.347,0.38,0.688,0.74]},{"time":1,"x":1.27,"y":-3.19,"curve":[0.377,0.61,0.719,1]},{"time":1.1667,"x":-5.03,"y":-2.07,"curve":[0.25,0,0.75,1]},{"time":1.3333,"x":-0.53,"y":-3.05}],"scale":[{"time":0,"x":1,"y":1,"curve":[0.25,0,0.75,1]},{"time":0.1333,"x":0.18,"y":1,"curve":[0.25,0,0.75,1]},{"time":0.2333,"x":0.104,"y":1.509,"curve":[0.25,0,0.75,1]},{"time":0.4,"x":0.939,"y":1,"curve":"stepped"},{"time":0.5667,"x":0.939,"y":1,"curve":[0.312,0.26,0.653,0.62]},{"time":0.7667,"x":0.455,"y":1,"curve":[0.332,0.33,0.668,0.67]},{"time":0.8333,"x":0.242,"y":1,"curve":[0.347,0.38,0.688,0.74]},{"time":1,"x":0.854,"y":1,"curve":[0.377,0.61,0.719,1]},{"time":1.1667,"x":0.819,"y":1}]},"Reye":{"rotate":[{"time":0,"angle":0,"curve":[0.25,0,0.75,1]},{"time":0.1333,"angle":3.95,"curve":[0.25,0,0.75,1]},{"time":0.2333,"angle":11.26,"curve":[0.25,0,0.75,1]},{"time":0.4,"angle":0.91,"curve":"stepped"},{"time":0.5667,"angle":0.91,"curve":[0.336,0.34,0.691,0.74]},{"time":0.7667,"angle":1.46,"curve":[0.378,0.61,0.721,1]},{"time":0.8333,"angle":1.75,"curve":"stepped"},{"time":1,"angle":1.75,"curve":"stepped"},{"time":1.1667,"angle":1.75,"curve":"stepped"},{"time":1.3333,"angle":1.75}],"translate":[{"time":0,"x":0,"y":0,"curve":[0.25,0,0.75,1]},{"time":0.2333,"x":1.94,"y":-6.63,"curve":[0.375,0.5,0.75,1]},{"time":0.4,"x":-0.08,"y":-3.46,"curve":[0.312,0.26,0.653,0.62]},{"time":0.5667,"x":-0.12,"y":-4.99,"curve":[0.312,0.26,0.653,0.62]},{"time":0.7667,"x":0,"y":0,"curve":"stepped"},{"time":0.8333,"x":0,"y":0,"curve":[0.347,0.38,0.688,0.74]},{"time":1,"x":1.27,"y":-3.19,"curve":[0.377,0.61,0.719,1]},{"time":1.1667,"x":-5.03,"y":-2.07,"curve":[0.25,0,0.75,1]},{"time":1.3333,"x":-0.53,"y":-3.05}],"scale":[{"time":0,"x":1,"y":1,"curve":[0.25,0,0.75,1]},{"time":0.1333,"x":0.14,"y":1,"curve":[0.25,0,0.75,1]},{"time":0.2333,"x":0.133,"y":1.509,"curve":[0.25,0,0.75,1]},{"time":0.4,"x":0.695,"y":1,"curve":"stepped"},{"time":0.5667,"x":0.695,"y":1,"curve":[0.312,0.26,0.653,0.62]},{"time":0.7667,"x":0.749,"y":1,"curve":[0.332,0.33,0.668,0.67]},{"time":0.8333,"x":0.242,"y":1,"curve":[0.347,0.38,0.688,0.74]},{"time":1,"x":1.258,"y":1,"curve":[0.377,0.61,0.719,1]},{"time":1.1667,"x":0.868,"y":1}]},"Lear":{"rotate":[{"time":0,"angle":0,"curve":"stepped"},{"time":0.1333,"angle":0,"curve":"stepped"},{"time":0.2667,"angle":0,"curve":"stepped"},{"time":0.4,"angle":0,"curve":[0.281,0,0.623,0.39]},{"time":0.5667,"angle":-29.78,"curve":[0.312,0.26,0.653,0.62]},{"time":0.7667,"angle":0,"curve":"stepped"},{"time":0.8333,"angle":0,"curve":"stepped"},{"time":1,"angle":0,"curve":"stepped"},{"time":1.1667,"angle":0,"curve":"stepped"},{"time":1.3333,"angle":0}],"translate":[{"time":0,"x":0,"y":0,"curve":[0.25,0,0.75,1]},{"time":0.1333,"x":-3,"y":6.24,"curve":[0.25,0,0.625,0.5]},{"time":0.2667,"x":-11.86,"y":-7.3,"curve":[0.375,0.5,0.75,1]},{"time":0.4,"x":2.71,"y":2.73,"curve":[0.281,0,0.623,0.39]},{"time":0.5667,"x":0,"y":0,"curve":[0.312,0.26,0.653,0.62]},{"time":0.7667,"x":-1.83,"y":-1.84,"curve":[0.332,0.33,0.668,0.67]},{"time":0.8333,"x":-21.34,"y":-21.47,"curve":[0.347,0.38,0.688,0.74]},{"time":1,"x":3.02,"y":3.03,"curve":[0.377,0.61,0.719,1]},{"time":1.1667,"x":-14.44,"y":-14.53,"curve":[0.25,0,0.75,1]},{"time":1.3333,"x":-3.72,"y":-3.75,"curve":[0.25,0,0.75,1]},{"time":1.4333,"x":-0.96,"y":-0.96}],"scale":[{"time":0.1333,"x":1,"y":1,"curve":"stepped"},{"time":0.2667,"x":1,"y":1,"curve":"stepped"},{"time":0.4,"x":1,"y":1,"curve":"stepped"},{"time":0.5667,"x":1,"y":1,"curve":"stepped"},{"time":0.7667,"x":1,"y":1,"curve":"stepped"},{"time":0.8333,"x":1,"y":1,"curve":"stepped"},{"time":1,"x":1,"y":1,"curve":"stepped"},{"time":1.1667,"x":1,"y":1}]},"Rear":{"rotate":[{"time":0,"angle":0,"curve":"stepped"},{"time":0.1333,"angle":0,"curve":"stepped"},{"time":0.2667,"angle":0,"curve":"stepped"},{"time":0.4,"angle":0,"curve":[0.281,0,0.623,0.39]},{"time":0.5667,"angle":4.29,"curve":[0.312,0.26,0.653,0.62]},{"time":0.7667,"angle":0,"curve":"stepped"},{"time":0.8333,"angle":0,"curve":"stepped"},{"time":1,"angle":0,"curve":"stepped"},{"time":1.1667,"angle":0,"curve":"stepped"},{"time":1.3333,"angle":0}],"translate":[{"time":0,"x":0,"y":0,"curve":[0.25,0,0.75,1]},{"time":0.1333,"x":6.58,"y":2.16,"curve":[0.25,0,0.625,0.5]},{"time":0.2667,"x":-5.69,"y":12.72,"curve":[0.375,0.5,0.75,1]},{"time":0.4,"x":1.46,"y":-1.9,"curve":[0.281,0,0.623,0.39]},{"time":0.5667,"x":-3.06,"y":3.41,"curve":[0.312,0.26,0.653,0.62]},{"time":0.7667,"x":-1.58,"y":2.05,"curve":[0.332,0.33,0.668,0.67]},{"time":0.8333,"x":-18.49,"y":23.96,"curve":[0.347,0.38,0.688,0.74]},{"time":1,"x":2.61,"y":-3.39,"curve":[0.377,0.61,0.719,1]},{"time":1.1667,"x":-12.52,"y":16.22,"curve":[0.25,0,0.75,1]},{"time":1.3333,"x":-3.23,"y":4.18,"curve":[0.25,0,0.75,1]},{"time":1.4333,"x":-1.47,"y":1.91}],"scale":[{"time":0.1333,"x":1,"y":1,"curve":"stepped"},{"time":0.2667,"x":1,"y":1,"curve":"stepped"},{"time":0.4,"x":1,"y":1,"curve":"stepped"},{"time":0.5667,"x":1,"y":1,"curve":"stepped"},{"time":0.7667,"x":1,"y":1,"curve":"stepped"},{"time":0.8333,"x":1,"y":1,"curve":"stepped"},{"time":1,"x":1,"y":1,"curve":"stepped"},{"time":1.1667,"x":1,"y":1}]},"xin":{"rotate":[{"time":0,"angle":0,"curve":[0.244,0,0.7,0.79]},{"time":0.8333,"angle":-12.52,"curve":[0.352,0.47,0.687,0.81]},{"time":1,"angle":-12.49,"curve":[0.348,0.66,0.682,1]},{"time":1.1,"angle":0,"curve":"stepped"},{"time":1.2,"angle":0,"curve":"stepped"},{"time":1.3333,"angle":0,"curve":"stepped"},{"time":1.4333,"angle":0,"curve":"stepped"},{"time":1.7,"angle":0}],"translate":[{"time":0,"x":0,"y":0,"curve":[0.244,0,0.7,0.79]},{"time":0.8333,"x":-171.36,"y":60.03,"curve":[0.345,0.4,0.678,0.74]},{"time":1,"x":-76.9,"y":17.23,"curve":[0.341,0.41,0.675,0.74]},{"time":1.1,"x":-13.33,"y":0.63,"curve":[0.25,0,0.75,1]},{"time":1.7,"x":0,"y":0}],"scale":[{"time":0,"x":1,"y":0,"curve":"stepped"},{"time":0.8333,"x":1,"y":0,"curve":[0.345,0.4,0.678,0.74]},{"time":1,"x":1,"y":0.445,"curve":[0.341,0.41,0.675,0.74]},{"time":1.1,"x":1,"y":1,"curve":[0.25,0,0.75,1]},{"time":1.2,"x":1,"y":0,"curve":[0.366,0.63,0.703,1]},{"time":1.3333,"x":1,"y":1,"curve":[0.25,0,0.75,1]},{"time":1.4333,"x":1,"y":0,"curve":[0.366,0.63,0.703,1]},{"time":1.7,"x":1,"y":1}]},"shadow":{"rotate":[{"time":0,"angle":0,"curve":"stepped"},{"time":1.3333,"angle":0}],"translate":[{"time":0,"x":-155.57,"y":-3.5,"curve":[0.25,0,0.75,1]},{"time":0.2667,"x":-76.04,"y":-3.5,"curve":[0.25,0,0.75,1]},{"time":0.4667,"x":8.73,"y":-3.5}],"scale":[{"time":0,"x":1,"y":1,"curve":[0.25,0,0.75,1]},{"time":0.2667,"x":0.764,"y":0.589,"curve":[0.25,0,0.75,1]},{"time":0.4667,"x":1,"y":1}]},"body":{"rotate":[{"time":0,"angle":0,"curve":[0.278,0,0.622,0.4]},{"time":0.1333,"angle":12.55,"curve":[0.313,0.27,0.655,0.63]},{"time":0.4,"angle":16.13,"curve":[0.34,0.36,0.674,0.69]},{"time":0.5667,"angle":-0.35,"curve":[0.25,0,0.75,1]},{"time":0.7667,"angle":-7.96,"curve":[0.25,0,0.75,1]},{"time":0.8333,"angle":0.35,"curve":[0.25,0,0.625,0.5]},{"time":1,"angle":-4.48,"curve":[0.375,0.5,0.75,1]},{"time":1.1667,"angle":-1.98,"curve":"stepped"},{"time":1.3333,"angle":-1.98,"curve":"stepped"},{"time":1.5,"angle":-1.98}],"translate":[{"time":0,"x":0,"y":0,"curve":"stepped"},{"time":0.1333,"x":0,"y":0,"curve":[0.25,0,0.75,1]},{"time":0.4,"x":16.03,"y":1.58,"curve":[0.351,0.42,0.686,0.76]},{"time":0.5667,"x":4.98,"y":3.52,"curve":[0.36,0.64,0.695,1]},{"time":0.7667,"x":-2.16,"y":1.44,"curve":[0.279,0,0.622,0.39]},{"time":0.8333,"x":6.9,"y":-0.11,"curve":"stepped"},{"time":1,"x":6.9,"y":-0.11,"curve":[0.382,0.55,0.741,1]},{"time":1.1667,"x":3.19,"y":0.13,"curve":[0.25,0,0.75,1]},{"time":1.3333,"x":6.9,"y":-0.11,"curve":"stepped"},{"time":1.5,"x":6.9,"y":-0.11}],"scale":[{"time":0,"x":1,"y":1,"curve":"stepped"},{"time":0.1333,"x":1,"y":1,"curve":[0.25,0,0.75,1]},{"time":0.4,"x":1.062,"y":1,"curve":[0.25,0,0.625,0.5]},{"time":0.5667,"x":0.907,"y":1,"curve":[0.375,0.5,0.75,1]},{"time":0.7667,"x":0.748,"y":1,"curve":[0.279,0,0.622,0.39]},{"time":0.8333,"x":1.121,"y":1,"curve":[0.309,0.26,0.664,0.66]},{"time":1,"x":1.06,"y":1,"curve":"stepped"},{"time":1.1667,"x":1.06,"y":1,"curve":[0.25,0,0.625,0.5]},{"time":1.3333,"x":1.03,"y":1,"curve":[0.375,0.5,0.75,1]},{"time":1.5,"x":1,"y":1}]},"text":{"rotate":[{"time":0,"angle":0,"curve":"stepped"},{"time":0.9,"angle":0,"curve":"stepped"},{"time":1.1,"angle":0,"curve":"stepped"},{"time":1.2333,"angle":0,"curve":"stepped"},{"time":1.4,"angle":0}],"translate":[{"time":0,"x":-116.67,"y":233.72,"curve":"stepped"},{"time":0.9,"x":-116.67,"y":233.72,"curve":[0.25,0,0.75,1]},{"time":1.1,"x":0,"y":0,"curve":"stepped"},{"time":1.2333,"x":0,"y":0,"curve":"stepped"},{"time":1.4,"x":0,"y":0}],"scale":[{"time":0,"x":0,"y":0,"curve":"stepped"},{"time":0.9,"x":0,"y":0,"curve":[0.25,0,0.75,1]},{"time":1.1,"x":1.16,"y":1.1,"curve":[0.25,0,0.75,1]},{"time":1.2333,"x":0.9,"y":0.9,"curve":[0.25,0,0.75,1]},{"time":1.4,"x":1,"y":1}]},"LIGHT":{"rotate":[{"time":0,"angle":0}],"translate":[{"time":0,"x":0,"y":0}],"scale":[{"time":0,"x":1,"y":1}]}}}}}